{
  "path": "/packages/gatsby-remark-copy-linked-files/",
  "result": {
    "data": {
      "markdownRemark": {
        "html": "<h1 id=\"gatsby-remark-copy-linked-files\"><a href=\"#gatsby-remark-copy-linked-files\" aria-label=\"gatsby remark copy linked files permalink\" class=\"anchor\"><svg aria-hidden=\"true\" focusable=\"false\" height=\"16\" version=\"1.1\" viewBox=\"0 0 16 16\" width=\"16\"><path fill-rule=\"evenodd\" d=\"M4 9h1v1H4c-1.5 0-3-1.69-3-3.5S2.55 3 4 3h4c1.45 0 3 1.69 3 3.5 0 1.41-.91 2.72-2 3.25V8.59c.58-.45 1-1.27 1-2.09C10 5.22 8.98 4 8 4H4c-.98 0-2 1.22-2 2.5S3 9 4 9zm9-3h-1v1h1c1 0 2 1.22 2 2.5S13.98 12 13 12H9c-.98 0-2-1.22-2-2.5 0-.83.42-1.64 1-2.09V6.25c-1.09.53-2 1.84-2 3.25C6 11.31 7.55 13 9 13h4c1.45 0 3-1.69 3-3.5S14.5 6 13 6z\"></path></svg></a>gatsby-remark-copy-linked-files</h1>\n<p>Copies local files linked to/from Markdown (<code class=\"language-text\">.md|.markdown</code>) files to the root directory (i.e., <code class=\"language-text\">public</code> folder).</p>\n<p><strong>A sample markdown file:</strong></p>\n<div class=\"gatsby-highlight\" data-language=\"md\"><pre class=\"language-md\"><code class=\"language-md\"><span class=\"token hr punctuation\">---</span>\n<span class=\"token title important\">title: My awesome blog post\n<span class=\"token punctuation\">---</span></span>\n\nHey everyone, I just made a sweet PDF with lots of interesting stuff in it.\n\n<span class=\"token url\">[<span class=\"token content\">Download it now</span>](my-awesome-pdf.pdf)</span></code></pre></div>\n<p><strong>When you build your site:</strong></p>\n<p>The <code class=\"language-text\">my-awesome-pdf.pdf</code> file will be copied to the root directory (i.e., <code class=\"language-text\">public/some-really-long-contenthash/my-awesome-pdf.pdf</code>) and the generated HTML page will be modified to point to it.</p>\n<blockquote>\n<p><strong>Note</strong>: The <code class=\"language-text\">my-awesome-pdf.pdf</code> file should be in the same directory as the markdown file.</p>\n</blockquote>\n<hr>\n<h2 id=\"install-plugin\"><a href=\"#install-plugin\" aria-label=\"install plugin permalink\" class=\"anchor\"><svg aria-hidden=\"true\" focusable=\"false\" height=\"16\" version=\"1.1\" viewBox=\"0 0 16 16\" width=\"16\"><path fill-rule=\"evenodd\" d=\"M4 9h1v1H4c-1.5 0-3-1.69-3-3.5S2.55 3 4 3h4c1.45 0 3 1.69 3 3.5 0 1.41-.91 2.72-2 3.25V8.59c.58-.45 1-1.27 1-2.09C10 5.22 8.98 4 8 4H4c-.98 0-2 1.22-2 2.5S3 9 4 9zm9-3h-1v1h1c1 0 2 1.22 2 2.5S13.98 12 13 12H9c-.98 0-2-1.22-2-2.5 0-.83.42-1.64 1-2.09V6.25c-1.09.53-2 1.84-2 3.25C6 11.31 7.55 13 9 13h4c1.45 0 3-1.69 3-3.5S14.5 6 13 6z\"></path></svg></a>Install plugin</h2>\n<p><code class=\"language-text\">npm install --save gatsby-remark-copy-linked-files</code></p>\n<h2 id=\"add-plugin-to-gatsby-config\"><a href=\"#add-plugin-to-gatsby-config\" aria-label=\"add plugin to gatsby config permalink\" class=\"anchor\"><svg aria-hidden=\"true\" focusable=\"false\" height=\"16\" version=\"1.1\" viewBox=\"0 0 16 16\" width=\"16\"><path fill-rule=\"evenodd\" d=\"M4 9h1v1H4c-1.5 0-3-1.69-3-3.5S2.55 3 4 3h4c1.45 0 3 1.69 3 3.5 0 1.41-.91 2.72-2 3.25V8.59c.58-.45 1-1.27 1-2.09C10 5.22 8.98 4 8 4H4c-.98 0-2 1.22-2 2.5S3 9 4 9zm9-3h-1v1h1c1 0 2 1.22 2 2.5S13.98 12 13 12H9c-.98 0-2-1.22-2-2.5 0-.83.42-1.64 1-2.09V6.25c-1.09.53-2 1.84-2 3.25C6 11.31 7.55 13 9 13h4c1.45 0 3-1.69 3-3.5S14.5 6 13 6z\"></path></svg></a>Add plugin to Gatsby Config</h2>\n<p><strong>Default settings:</strong></p>\n<p>Add <code class=\"language-text\">gatsby-remark-copy-linked-files</code> plugin as a plugin to <a href=\"https://www.gatsbyjs.org/packages/gatsby-transformer-remark/\"><code class=\"language-text\">gatsby-transformer-remark</code></a>:</p>\n<div class=\"gatsby-highlight\" data-language=\"javascript\"><pre class=\"language-javascript\"><code class=\"language-javascript\"><span class=\"token comment\">// In your gatsby-config.js</span>\n\n<span class=\"token comment\">// add plugin by name only</span>\nplugins<span class=\"token punctuation\">:</span> <span class=\"token punctuation\">[</span>\n  <span class=\"token punctuation\">{</span>\n    resolve<span class=\"token punctuation\">:</span> <span class=\"token template-string\"><span class=\"token template-punctuation string\">`</span><span class=\"token string\">gatsby-transformer-remark</span><span class=\"token template-punctuation string\">`</span></span><span class=\"token punctuation\">,</span>\n    options<span class=\"token punctuation\">:</span> <span class=\"token punctuation\">{</span>\n      plugins<span class=\"token punctuation\">:</span> <span class=\"token punctuation\">[</span><span class=\"token template-string\"><span class=\"token template-punctuation string\">`</span><span class=\"token string\">gatsby-remark-copy-linked-files</span><span class=\"token template-punctuation string\">`</span></span><span class=\"token punctuation\">]</span><span class=\"token punctuation\">,</span>\n    <span class=\"token punctuation\">}</span><span class=\"token punctuation\">,</span>\n  <span class=\"token punctuation\">}</span><span class=\"token punctuation\">,</span>\n<span class=\"token punctuation\">]</span></code></pre></div>\n<p><strong>Custom settings:</strong></p>\n<div class=\"gatsby-highlight\" data-language=\"js\"><pre class=\"language-js\"><code class=\"language-js\"><span class=\"token comment\">// In your gatsby-config.js</span>\n\n<span class=\"token comment\">// add plugin by name and options</span>\nplugins<span class=\"token punctuation\">:</span> <span class=\"token punctuation\">[</span>\n  <span class=\"token punctuation\">{</span>\n    resolve<span class=\"token punctuation\">:</span> <span class=\"token template-string\"><span class=\"token template-punctuation string\">`</span><span class=\"token string\">gatsby-transformer-remark</span><span class=\"token template-punctuation string\">`</span></span><span class=\"token punctuation\">,</span>\n    options<span class=\"token punctuation\">:</span> <span class=\"token punctuation\">{</span>\n      plugins<span class=\"token punctuation\">:</span> <span class=\"token punctuation\">[</span>\n        <span class=\"token punctuation\">{</span>\n          resolve<span class=\"token punctuation\">:</span> <span class=\"token template-string\"><span class=\"token template-punctuation string\">`</span><span class=\"token string\">gatsby-remark-copy-linked-files</span><span class=\"token template-punctuation string\">`</span></span><span class=\"token punctuation\">,</span>\n          options<span class=\"token punctuation\">:</span> <span class=\"token punctuation\">{</span>\n            destinationDir<span class=\"token punctuation\">:</span> <span class=\"token template-string\"><span class=\"token template-punctuation string\">`</span><span class=\"token string\">path/to/dir</span><span class=\"token template-punctuation string\">`</span></span><span class=\"token punctuation\">,</span>\n            ignoreFileExtensions<span class=\"token punctuation\">:</span> <span class=\"token punctuation\">[</span><span class=\"token template-string\"><span class=\"token template-punctuation string\">`</span><span class=\"token string\">png</span><span class=\"token template-punctuation string\">`</span></span><span class=\"token punctuation\">,</span> <span class=\"token template-string\"><span class=\"token template-punctuation string\">`</span><span class=\"token string\">jpg</span><span class=\"token template-punctuation string\">`</span></span><span class=\"token punctuation\">,</span> <span class=\"token template-string\"><span class=\"token template-punctuation string\">`</span><span class=\"token string\">jpeg</span><span class=\"token template-punctuation string\">`</span></span><span class=\"token punctuation\">,</span> <span class=\"token template-string\"><span class=\"token template-punctuation string\">`</span><span class=\"token string\">bmp</span><span class=\"token template-punctuation string\">`</span></span><span class=\"token punctuation\">,</span> <span class=\"token template-string\"><span class=\"token template-punctuation string\">`</span><span class=\"token string\">tiff</span><span class=\"token template-punctuation string\">`</span></span><span class=\"token punctuation\">]</span><span class=\"token punctuation\">,</span>\n          <span class=\"token punctuation\">}</span><span class=\"token punctuation\">,</span>\n        <span class=\"token punctuation\">}</span><span class=\"token punctuation\">,</span>\n      <span class=\"token punctuation\">]</span><span class=\"token punctuation\">,</span>\n    <span class=\"token punctuation\">}</span><span class=\"token punctuation\">,</span>\n  <span class=\"token punctuation\">}</span><span class=\"token punctuation\">,</span>\n<span class=\"token punctuation\">]</span></code></pre></div>\n<hr>\n<h2 id=\"custom-set-where-to-copy-the-files-using-destinationdir\"><a href=\"#custom-set-where-to-copy-the-files-using-destinationdir\" aria-label=\"custom set where to copy the files using destinationdir permalink\" class=\"anchor\"><svg aria-hidden=\"true\" focusable=\"false\" height=\"16\" version=\"1.1\" viewBox=\"0 0 16 16\" width=\"16\"><path fill-rule=\"evenodd\" d=\"M4 9h1v1H4c-1.5 0-3-1.69-3-3.5S2.55 3 4 3h4c1.45 0 3 1.69 3 3.5 0 1.41-.91 2.72-2 3.25V8.59c.58-.45 1-1.27 1-2.09C10 5.22 8.98 4 8 4H4c-.98 0-2 1.22-2 2.5S3 9 4 9zm9-3h-1v1h1c1 0 2 1.22 2 2.5S13.98 12 13 12H9c-.98 0-2-1.22-2-2.5 0-.83.42-1.64 1-2.09V6.25c-1.09.53-2 1.84-2 3.25C6 11.31 7.55 13 9 13h4c1.45 0 3-1.69 3-3.5S14.5 6 13 6z\"></path></svg></a>Custom set where to copy the files using <code class=\"language-text\">destinationDir</code></h2>\n<p>By default, all files will be copied to the root directory (i.e., <code class=\"language-text\">public</code> folder) in the following format: <code class=\"language-text\">contentHash/fileName.ext</code>.</p>\n<blockquote>\n<p>For example, <code class=\"language-text\">[Download it now](my-awesome-pdf.pdf)</code> will copy the file <code class=\"language-text\">my-awesome-pdf.pdf</code> to something like <code class=\"language-text\">public/2a0039f3a61f4510f41678438e4c863a/my-awesome-pdf.pdf</code></p>\n</blockquote>\n<h3 id=\"simple-usage\"><a href=\"#simple-usage\" aria-label=\"simple usage permalink\" class=\"anchor\"><svg aria-hidden=\"true\" focusable=\"false\" height=\"16\" version=\"1.1\" viewBox=\"0 0 16 16\" width=\"16\"><path fill-rule=\"evenodd\" d=\"M4 9h1v1H4c-1.5 0-3-1.69-3-3.5S2.55 3 4 3h4c1.45 0 3 1.69 3 3.5 0 1.41-.91 2.72-2 3.25V8.59c.58-.45 1-1.27 1-2.09C10 5.22 8.98 4 8 4H4c-.98 0-2 1.22-2 2.5S3 9 4 9zm9-3h-1v1h1c1 0 2 1.22 2 2.5S13.98 12 13 12H9c-.98 0-2-1.22-2-2.5 0-.83.42-1.64 1-2.09V6.25c-1.09.53-2 1.84-2 3.25C6 11.31 7.55 13 9 13h4c1.45 0 3-1.69 3-3.5S14.5 6 13 6z\"></path></svg></a>Simple usage</h3>\n<p>To change this, set <code class=\"language-text\">destinationDir</code> to a path of your own choosing (i.e., <code class=\"language-text\">path/to/dir</code>).</p>\n<div class=\"gatsby-highlight\" data-language=\"js\"><pre class=\"language-js\"><code class=\"language-js\"><span class=\"token comment\">// In your gatsby-config.js</span>\nplugins<span class=\"token punctuation\">:</span> <span class=\"token punctuation\">[</span>\n  <span class=\"token punctuation\">{</span>\n    resolve<span class=\"token punctuation\">:</span> <span class=\"token template-string\"><span class=\"token template-punctuation string\">`</span><span class=\"token string\">gatsby-transformer-remark</span><span class=\"token template-punctuation string\">`</span></span><span class=\"token punctuation\">,</span>\n    options<span class=\"token punctuation\">:</span> <span class=\"token punctuation\">{</span>\n      plugins<span class=\"token punctuation\">:</span> <span class=\"token punctuation\">[</span>\n        <span class=\"token punctuation\">{</span>\n          resolve<span class=\"token punctuation\">:</span> <span class=\"token string\">\"gatsby-remark-copy-linked-files\"</span><span class=\"token punctuation\">,</span>\n          options<span class=\"token punctuation\">:</span> <span class=\"token punctuation\">{</span>\n            destinationDir<span class=\"token punctuation\">:</span> <span class=\"token string\">\"path/to/dir\"</span><span class=\"token punctuation\">,</span>\n          <span class=\"token punctuation\">}</span><span class=\"token punctuation\">,</span>\n        <span class=\"token punctuation\">}</span><span class=\"token punctuation\">,</span>\n      <span class=\"token punctuation\">]</span><span class=\"token punctuation\">,</span>\n    <span class=\"token punctuation\">}</span><span class=\"token punctuation\">,</span>\n  <span class=\"token punctuation\">}</span><span class=\"token punctuation\">,</span>\n<span class=\"token punctuation\">]</span></code></pre></div>\n<blockquote>\n<p>So now, <code class=\"language-text\">[Download it now](my-awesome-pdf.pdf)</code> will copy the file <code class=\"language-text\">my-awesome-pdf.pdf</code> to <code class=\"language-text\">public/path/to/dir/2a0039f3a61f4510f41678438e4c863a/my-awesome-pdf.pdf</code></p>\n</blockquote>\n<h3 id=\"advanced-usage\"><a href=\"#advanced-usage\" aria-label=\"advanced usage permalink\" class=\"anchor\"><svg aria-hidden=\"true\" focusable=\"false\" height=\"16\" version=\"1.1\" viewBox=\"0 0 16 16\" width=\"16\"><path fill-rule=\"evenodd\" d=\"M4 9h1v1H4c-1.5 0-3-1.69-3-3.5S2.55 3 4 3h4c1.45 0 3 1.69 3 3.5 0 1.41-.91 2.72-2 3.25V8.59c.58-.45 1-1.27 1-2.09C10 5.22 8.98 4 8 4H4c-.98 0-2 1.22-2 2.5S3 9 4 9zm9-3h-1v1h1c1 0 2 1.22 2 2.5S13.98 12 13 12H9c-.98 0-2-1.22-2-2.5 0-.83.42-1.64 1-2.09V6.25c-1.09.53-2 1.84-2 3.25C6 11.31 7.55 13 9 13h4c1.45 0 3-1.69 3-3.5S14.5 6 13 6z\"></path></svg></a>Advanced usage</h3>\n<p>For more advanced control, set <code class=\"language-text\">destinationDir</code> to a function expression using properties <code class=\"language-text\">name</code> and/or <code class=\"language-text\">hash</code> to specify the path.</p>\n<p><strong>Examples:</strong></p>\n<div class=\"gatsby-highlight\" data-language=\"js\"><pre class=\"language-js\"><code class=\"language-js\"># save <span class=\"token template-string\"><span class=\"token template-punctuation string\">`</span><span class=\"token string\">my-awesome-pdf.pdf</span><span class=\"token template-punctuation string\">`</span></span> to <span class=\"token template-string\"><span class=\"token template-punctuation string\">`</span><span class=\"token string\">public/my-awesome-pdf.pdf</span><span class=\"token template-punctuation string\">`</span></span>\n<span class=\"token function-variable function\">destinationDir</span><span class=\"token punctuation\">:</span> <span class=\"token parameter\">f</span> <span class=\"token operator\">=></span> <span class=\"token template-string\"><span class=\"token template-punctuation string\">`</span><span class=\"token interpolation\"><span class=\"token interpolation-punctuation punctuation\">${</span>f<span class=\"token punctuation\">.</span>name<span class=\"token interpolation-punctuation punctuation\">}</span></span><span class=\"token template-punctuation string\">`</span></span>\n\n# save <span class=\"token template-string\"><span class=\"token template-punctuation string\">`</span><span class=\"token string\">my-awesome-pdf.pdf</span><span class=\"token template-punctuation string\">`</span></span> to <span class=\"token template-string\"><span class=\"token template-punctuation string\">`</span><span class=\"token string\">public/2a0039f3a61f4510f41678438e4c863a.pdf</span><span class=\"token template-punctuation string\">`</span></span>\n<span class=\"token function-variable function\">destinationDir</span><span class=\"token punctuation\">:</span> <span class=\"token parameter\">f</span> <span class=\"token operator\">=></span> <span class=\"token template-string\"><span class=\"token template-punctuation string\">`</span><span class=\"token interpolation\"><span class=\"token interpolation-punctuation punctuation\">${</span>f<span class=\"token punctuation\">.</span>hash<span class=\"token interpolation-punctuation punctuation\">}</span></span><span class=\"token template-punctuation string\">`</span></span>\n\n# save <span class=\"token template-string\"><span class=\"token template-punctuation string\">`</span><span class=\"token string\">my-awesome-pdf.pdf</span><span class=\"token template-punctuation string\">`</span></span> to <span class=\"token template-string\"><span class=\"token template-punctuation string\">`</span><span class=\"token string\">public/downloads/2a0039f3a61f4510f41678438e4c863a/my-awesome-pdf.pdf</span><span class=\"token template-punctuation string\">`</span></span>\n<span class=\"token function-variable function\">destinationDir</span><span class=\"token punctuation\">:</span> <span class=\"token parameter\">f</span> <span class=\"token operator\">=></span> <span class=\"token template-string\"><span class=\"token template-punctuation string\">`</span><span class=\"token string\">downloads/</span><span class=\"token interpolation\"><span class=\"token interpolation-punctuation punctuation\">${</span>f<span class=\"token punctuation\">.</span>hash<span class=\"token interpolation-punctuation punctuation\">}</span></span><span class=\"token string\">/</span><span class=\"token interpolation\"><span class=\"token interpolation-punctuation punctuation\">${</span>f<span class=\"token punctuation\">.</span>name<span class=\"token interpolation-punctuation punctuation\">}</span></span><span class=\"token template-punctuation string\">`</span></span>\n\n# save <span class=\"token template-string\"><span class=\"token template-punctuation string\">`</span><span class=\"token string\">my-awesome-pdf.pdf</span><span class=\"token template-punctuation string\">`</span></span> to <span class=\"token template-string\"><span class=\"token template-punctuation string\">`</span><span class=\"token string\">public/downloads/2a0039f3a61f4510f41678438e4c863a-my-awesome-pdf.pdf</span><span class=\"token template-punctuation string\">`</span></span>\n<span class=\"token function-variable function\">destinationDir</span><span class=\"token punctuation\">:</span> <span class=\"token parameter\">f</span> <span class=\"token operator\">=></span> <span class=\"token template-string\"><span class=\"token template-punctuation string\">`</span><span class=\"token string\">downloads/</span><span class=\"token interpolation\"><span class=\"token interpolation-punctuation punctuation\">${</span>f<span class=\"token punctuation\">.</span>hash<span class=\"token interpolation-punctuation punctuation\">}</span></span><span class=\"token string\">-</span><span class=\"token interpolation\"><span class=\"token interpolation-punctuation punctuation\">${</span>f<span class=\"token punctuation\">.</span>name<span class=\"token interpolation-punctuation punctuation\">}</span></span><span class=\"token template-punctuation string\">`</span></span>\n\n# save <span class=\"token template-string\"><span class=\"token template-punctuation string\">`</span><span class=\"token string\">my-awesome-pdf.pdf</span><span class=\"token template-punctuation string\">`</span></span> to <span class=\"token template-string\"><span class=\"token template-punctuation string\">`</span><span class=\"token string\">public/my-awesome-pdf/2a0039f3a61f4510f41678438e4c863a.pdf</span><span class=\"token template-punctuation string\">`</span></span>\n<span class=\"token function-variable function\">destinationDir</span><span class=\"token punctuation\">:</span> <span class=\"token parameter\">f</span> <span class=\"token operator\">=></span> <span class=\"token template-string\"><span class=\"token template-punctuation string\">`</span><span class=\"token interpolation\"><span class=\"token interpolation-punctuation punctuation\">${</span>f<span class=\"token punctuation\">.</span>name<span class=\"token interpolation-punctuation punctuation\">}</span></span><span class=\"token string\">/</span><span class=\"token interpolation\"><span class=\"token interpolation-punctuation punctuation\">${</span>f<span class=\"token punctuation\">.</span>hash<span class=\"token interpolation-punctuation punctuation\">}</span></span><span class=\"token template-punctuation string\">`</span></span>\n\n# save <span class=\"token template-string\"><span class=\"token template-punctuation string\">`</span><span class=\"token string\">my-awesome-pdf.pdf</span><span class=\"token template-punctuation string\">`</span></span> to <span class=\"token template-string\"><span class=\"token template-punctuation string\">`</span><span class=\"token string\">public/path/to/dir/hello-my-awesome-pdf+2a0039f3a61f4510f41678438e4c863a_world.pdf</span><span class=\"token template-punctuation string\">`</span></span>\n<span class=\"token function-variable function\">destinationDir</span><span class=\"token punctuation\">:</span> <span class=\"token parameter\">f</span> <span class=\"token operator\">=></span> <span class=\"token template-string\"><span class=\"token template-punctuation string\">`</span><span class=\"token string\">path/to/dir/hello-</span><span class=\"token interpolation\"><span class=\"token interpolation-punctuation punctuation\">${</span>f<span class=\"token punctuation\">.</span>name<span class=\"token interpolation-punctuation punctuation\">}</span></span><span class=\"token string\">+</span><span class=\"token interpolation\"><span class=\"token interpolation-punctuation punctuation\">${</span>f<span class=\"token punctuation\">.</span>hash<span class=\"token interpolation-punctuation punctuation\">}</span></span><span class=\"token string\">_world</span><span class=\"token template-punctuation string\">`</span></span></code></pre></div>\n<blockquote>\n<p><strong>Note:</strong> Make sure you use either <code class=\"language-text\">name</code> or <code class=\"language-text\">hash</code> property in your function expression!\nIf you don’t include both <code class=\"language-text\">name</code> and <code class=\"language-text\">hash</code> properties in your function expression, <code class=\"language-text\">gatsby-remark-copy-linked-files</code> plugin will resolve the function expression to a string value and use default settings as a fallback mechanism to prevent your local files from getting copied with the same name (causing files to get overwritten).</p>\n</blockquote>\n<div class=\"gatsby-highlight\" data-language=\"js\"><pre class=\"language-js\"><code class=\"language-js\"># Note<span class=\"token punctuation\">:</span> <span class=\"token template-string\"><span class=\"token template-punctuation string\">`</span><span class=\"token string\">my-awesome-pdf.pdf</span><span class=\"token template-punctuation string\">`</span></span> is saved to <span class=\"token template-string\"><span class=\"token template-punctuation string\">`</span><span class=\"token string\">public/hello/2a0039f3a61f4510f41678438e4c863a/my-awesome-pdf.pdf</span><span class=\"token template-punctuation string\">`</span></span>\n# because <span class=\"token template-string\"><span class=\"token template-punctuation string\">`</span><span class=\"token string\">name</span><span class=\"token template-punctuation string\">`</span></span> and <span class=\"token template-string\"><span class=\"token template-punctuation string\">`</span><span class=\"token string\">hash</span><span class=\"token template-punctuation string\">`</span></span> properties are not referenced <span class=\"token keyword\">in</span> the <span class=\"token keyword\">function</span> expression<span class=\"token punctuation\">.</span>\n# So these <span class=\"token keyword\">function</span> expressions are treated the same way\n<span class=\"token function-variable function\">destinationDir</span><span class=\"token punctuation\">:</span> <span class=\"token parameter\">_</span> <span class=\"token operator\">=></span> <span class=\"token template-string\"><span class=\"token template-punctuation string\">`</span><span class=\"token string\">hello</span><span class=\"token template-punctuation string\">`</span></span>\ndestinationDir<span class=\"token punctuation\">:</span> <span class=\"token template-string\"><span class=\"token template-punctuation string\">`</span><span class=\"token string\">hello</span><span class=\"token template-punctuation string\">`</span></span></code></pre></div>\n<h3 id=\"caveat-error-thrown-if-destinationdir-points-outside-the-root-directory-ie-public-folder\"><a href=\"#caveat-error-thrown-if-destinationdir-points-outside-the-root-directory-ie-public-folder\" aria-label=\"caveat error thrown if destinationdir points outside the root directory ie public folder permalink\" class=\"anchor\"><svg aria-hidden=\"true\" focusable=\"false\" height=\"16\" version=\"1.1\" viewBox=\"0 0 16 16\" width=\"16\"><path fill-rule=\"evenodd\" d=\"M4 9h1v1H4c-1.5 0-3-1.69-3-3.5S2.55 3 4 3h4c1.45 0 3 1.69 3 3.5 0 1.41-.91 2.72-2 3.25V8.59c.58-.45 1-1.27 1-2.09C10 5.22 8.98 4 8 4H4c-.98 0-2 1.22-2 2.5S3 9 4 9zm9-3h-1v1h1c1 0 2 1.22 2 2.5S13.98 12 13 12H9c-.98 0-2-1.22-2-2.5 0-.83.42-1.64 1-2.09V6.25c-1.09.53-2 1.84-2 3.25C6 11.31 7.55 13 9 13h4c1.45 0 3-1.69 3-3.5S14.5 6 13 6z\"></path></svg></a>Caveat: Error thrown if <code class=\"language-text\">destinationDir</code> points outside the root directory (i.e. <code class=\"language-text\">public</code> folder)</h3>\n<blockquote>\n<p><strong>Note:</strong> An error will be thrown if the destination points outside the root directory (i.e. <code class=\"language-text\">public</code> folder).</p>\n</blockquote>\n<p><strong>Correct:</strong></p>\n<div class=\"gatsby-highlight\" data-language=\"js\"><pre class=\"language-js\"><code class=\"language-js\"># saves to <span class=\"token template-string\"><span class=\"token template-punctuation string\">`</span><span class=\"token string\">public/path/to/dir/</span><span class=\"token template-punctuation string\">`</span></span>\ndestinationDir<span class=\"token punctuation\">:</span> <span class=\"token template-string\"><span class=\"token template-punctuation string\">`</span><span class=\"token string\">path/to/dir</span><span class=\"token template-punctuation string\">`</span></span>\n\n# saves to <span class=\"token template-string\"><span class=\"token template-punctuation string\">`</span><span class=\"token string\">public/path/to/dir/</span><span class=\"token template-punctuation string\">`</span></span>\n<span class=\"token function-variable function\">destinationDir</span><span class=\"token punctuation\">:</span> <span class=\"token parameter\">_</span> <span class=\"token operator\">=></span> <span class=\"token template-string\"><span class=\"token template-punctuation string\">`</span><span class=\"token string\">path/to/dir</span><span class=\"token template-punctuation string\">`</span></span>\n\n# saves to <span class=\"token template-string\"><span class=\"token template-punctuation string\">`</span><span class=\"token string\">public/path/to/dir/fileName.ext</span><span class=\"token template-punctuation string\">`</span></span>\n<span class=\"token function-variable function\">destinationDir</span><span class=\"token punctuation\">:</span> <span class=\"token parameter\">f</span> <span class=\"token operator\">=></span> <span class=\"token template-string\"><span class=\"token template-punctuation string\">`</span><span class=\"token string\">path/to/dir/</span><span class=\"token interpolation\"><span class=\"token interpolation-punctuation punctuation\">${</span>f<span class=\"token punctuation\">.</span>name<span class=\"token interpolation-punctuation punctuation\">}</span></span><span class=\"token template-punctuation string\">`</span></span>\n\n# saves to <span class=\"token template-string\"><span class=\"token template-punctuation string\">`</span><span class=\"token string\">public/contentHash.ext</span><span class=\"token template-punctuation string\">`</span></span>\n<span class=\"token function-variable function\">destinationDir</span><span class=\"token punctuation\">:</span> <span class=\"token parameter\">f</span> <span class=\"token operator\">=></span> <span class=\"token template-string\"><span class=\"token template-punctuation string\">`</span><span class=\"token interpolation\"><span class=\"token interpolation-punctuation punctuation\">${</span>f<span class=\"token punctuation\">.</span>hash<span class=\"token interpolation-punctuation punctuation\">}</span></span><span class=\"token template-punctuation string\">`</span></span></code></pre></div>\n<p><strong>Error thrown:</strong></p>\n<div class=\"gatsby-highlight\" data-language=\"js\"><pre class=\"language-js\"><code class=\"language-js\"># cannot save outside root <span class=\"token function\">directory</span> <span class=\"token punctuation\">(</span>i<span class=\"token punctuation\">.</span>e<span class=\"token punctuation\">.</span><span class=\"token punctuation\">,</span> outside <span class=\"token template-string\"><span class=\"token template-punctuation string\">`</span><span class=\"token string\">public</span><span class=\"token template-punctuation string\">`</span></span> folder<span class=\"token punctuation\">)</span>\ndestinationDir<span class=\"token punctuation\">:</span> <span class=\"token template-string\"><span class=\"token template-punctuation string\">`</span><span class=\"token string\">../path/to/dir</span><span class=\"token template-punctuation string\">`</span></span>\n<span class=\"token function-variable function\">destinationDir</span><span class=\"token punctuation\">:</span> <span class=\"token parameter\">_</span> <span class=\"token operator\">=></span> <span class=\"token template-string\"><span class=\"token template-punctuation string\">`</span><span class=\"token string\">../path/to/dir</span><span class=\"token template-punctuation string\">`</span></span>\n<span class=\"token function-variable function\">destinationDir</span><span class=\"token punctuation\">:</span> <span class=\"token parameter\">f</span> <span class=\"token operator\">=></span> <span class=\"token template-string\"><span class=\"token template-punctuation string\">`</span><span class=\"token string\">../path/to/dir/</span><span class=\"token interpolation\"><span class=\"token interpolation-punctuation punctuation\">${</span>f<span class=\"token punctuation\">.</span>name<span class=\"token interpolation-punctuation punctuation\">}</span></span><span class=\"token template-punctuation string\">`</span></span>\n<span class=\"token function-variable function\">destinationDir</span><span class=\"token punctuation\">:</span> <span class=\"token parameter\">f</span> <span class=\"token operator\">=></span> <span class=\"token template-string\"><span class=\"token template-punctuation string\">`</span><span class=\"token string\">../</span><span class=\"token interpolation\"><span class=\"token interpolation-punctuation punctuation\">${</span>f<span class=\"token punctuation\">.</span>hash<span class=\"token interpolation-punctuation punctuation\">}</span></span><span class=\"token template-punctuation string\">`</span></span></code></pre></div>\n<hr>\n<h3 id=\"custom-set-which-file-types-to-ignore-using-ignorefileextensions\"><a href=\"#custom-set-which-file-types-to-ignore-using-ignorefileextensions\" aria-label=\"custom set which file types to ignore using ignorefileextensions permalink\" class=\"anchor\"><svg aria-hidden=\"true\" focusable=\"false\" height=\"16\" version=\"1.1\" viewBox=\"0 0 16 16\" width=\"16\"><path fill-rule=\"evenodd\" d=\"M4 9h1v1H4c-1.5 0-3-1.69-3-3.5S2.55 3 4 3h4c1.45 0 3 1.69 3 3.5 0 1.41-.91 2.72-2 3.25V8.59c.58-.45 1-1.27 1-2.09C10 5.22 8.98 4 8 4H4c-.98 0-2 1.22-2 2.5S3 9 4 9zm9-3h-1v1h1c1 0 2 1.22 2 2.5S13.98 12 13 12H9c-.98 0-2-1.22-2-2.5 0-.83.42-1.64 1-2.09V6.25c-1.09.53-2 1.84-2 3.25C6 11.31 7.55 13 9 13h4c1.45 0 3-1.69 3-3.5S14.5 6 13 6z\"></path></svg></a>Custom set which file types to ignore using <code class=\"language-text\">ignoreFileExtensions</code></h3>\n<p>By default, the file types that this plugin ignores are: <code class=\"language-text\">png</code>, <code class=\"language-text\">jpg</code>, <code class=\"language-text\">jpeg</code>, <code class=\"language-text\">bmp</code>, <code class=\"language-text\">tiff</code>.</p>\n<blockquote>\n<p>For example, <code class=\"language-text\">[Download it now](image.png)</code> will be ignored and not copied to the root dir (i.e. <code class=\"language-text\">public</code> folder)</p>\n</blockquote>\n<p>To change this, set <code class=\"language-text\">ignoreFileExtensions</code> to an array of extensions to ignore (i.e., an empty array <code class=\"language-text\">[]</code> to ignore nothing).</p>\n<div class=\"gatsby-highlight\" data-language=\"javascript\"><pre class=\"language-javascript\"><code class=\"language-javascript\"><span class=\"token comment\">// In your gatsby-config.js</span>\nplugins<span class=\"token punctuation\">:</span> <span class=\"token punctuation\">[</span>\n  <span class=\"token punctuation\">{</span>\n    resolve<span class=\"token punctuation\">:</span> <span class=\"token template-string\"><span class=\"token template-punctuation string\">`</span><span class=\"token string\">gatsby-transformer-remark</span><span class=\"token template-punctuation string\">`</span></span><span class=\"token punctuation\">,</span>\n    options<span class=\"token punctuation\">:</span> <span class=\"token punctuation\">{</span>\n      plugins<span class=\"token punctuation\">:</span> <span class=\"token punctuation\">[</span>\n        <span class=\"token punctuation\">{</span>\n          resolve<span class=\"token punctuation\">:</span> <span class=\"token string\">\"gatsby-remark-copy-linked-files\"</span><span class=\"token punctuation\">,</span>\n          options<span class=\"token punctuation\">:</span> <span class=\"token punctuation\">{</span>\n            <span class=\"token comment\">// `ignoreFileExtensions` defaults to [`png`, `jpg`, `jpeg`, `bmp`, `tiff`]</span>\n            <span class=\"token comment\">// as we assume you'll use gatsby-remark-images to handle</span>\n            <span class=\"token comment\">// images in markdown as it automatically creates responsive</span>\n            <span class=\"token comment\">// versions of images.</span>\n            <span class=\"token comment\">//</span>\n            <span class=\"token comment\">// If you'd like to not use gatsby-remark-images and just copy your</span>\n            <span class=\"token comment\">// original images to the public directory, set</span>\n            <span class=\"token comment\">// `ignoreFileExtensions` to an empty array.</span>\n            ignoreFileExtensions<span class=\"token punctuation\">:</span> <span class=\"token punctuation\">[</span><span class=\"token punctuation\">]</span><span class=\"token punctuation\">,</span>\n          <span class=\"token punctuation\">}</span><span class=\"token punctuation\">,</span>\n        <span class=\"token punctuation\">}</span><span class=\"token punctuation\">,</span>\n      <span class=\"token punctuation\">]</span><span class=\"token punctuation\">,</span>\n    <span class=\"token punctuation\">}</span><span class=\"token punctuation\">,</span>\n  <span class=\"token punctuation\">}</span><span class=\"token punctuation\">,</span>\n<span class=\"token punctuation\">]</span></code></pre></div>\n<blockquote>\n<p>So now, <code class=\"language-text\">[Download it now](image.png)</code> will be copied to the root dir (i.e. <code class=\"language-text\">public</code> folder)</p>\n</blockquote>\n<hr>\n<h3 id=\"supported-markdown-tags\"><a href=\"#supported-markdown-tags\" aria-label=\"supported markdown tags permalink\" class=\"anchor\"><svg aria-hidden=\"true\" focusable=\"false\" height=\"16\" version=\"1.1\" viewBox=\"0 0 16 16\" width=\"16\"><path fill-rule=\"evenodd\" d=\"M4 9h1v1H4c-1.5 0-3-1.69-3-3.5S2.55 3 4 3h4c1.45 0 3 1.69 3 3.5 0 1.41-.91 2.72-2 3.25V8.59c.58-.45 1-1.27 1-2.09C10 5.22 8.98 4 8 4H4c-.98 0-2 1.22-2 2.5S3 9 4 9zm9-3h-1v1h1c1 0 2 1.22 2 2.5S13.98 12 13 12H9c-.98 0-2-1.22-2-2.5 0-.83.42-1.64 1-2.09V6.25c-1.09.53-2 1.84-2 3.25C6 11.31 7.55 13 9 13h4c1.45 0 3-1.69 3-3.5S14.5 6 13 6z\"></path></svg></a>Supported Markdown tags</h3>\n<ul>\n<li>img - <code class=\"language-text\">![Image](my-img.png)</code></li>\n<li>link - <code class=\"language-text\">[Link](myFile.txt)</code></li>\n</ul>\n<h3 id=\"supported-html-tags\"><a href=\"#supported-html-tags\" aria-label=\"supported html tags permalink\" class=\"anchor\"><svg aria-hidden=\"true\" focusable=\"false\" height=\"16\" version=\"1.1\" viewBox=\"0 0 16 16\" width=\"16\"><path fill-rule=\"evenodd\" d=\"M4 9h1v1H4c-1.5 0-3-1.69-3-3.5S2.55 3 4 3h4c1.45 0 3 1.69 3 3.5 0 1.41-.91 2.72-2 3.25V8.59c.58-.45 1-1.27 1-2.09C10 5.22 8.98 4 8 4H4c-.98 0-2 1.22-2 2.5S3 9 4 9zm9-3h-1v1h1c1 0 2 1.22 2 2.5S13.98 12 13 12H9c-.98 0-2-1.22-2-2.5 0-.83.42-1.64 1-2.09V6.25c-1.09.53-2 1.84-2 3.25C6 11.31 7.55 13 9 13h4c1.45 0 3-1.69 3-3.5S14.5 6 13 6z\"></path></svg></a>Supported HTML tags</h3>\n<ul>\n<li><code class=\"language-text\">&lt;img /&gt;</code></li>\n<li><code class=\"language-text\">&lt;video /&gt;</code></li>\n<li><code class=\"language-text\">&lt;audio /&gt;</code></li>\n<li><code class=\"language-text\">&lt;a /&gt;</code></li>\n</ul>",
        "excerpt": "gatsby-remark-copy-linked-files Copies local files linked to/from Markdown () files to the root directory (i.e.,  folder). A sample markdown…",
        "timeToRead": 5,
        "fields": {
          "title": "gatsby-remark-copy-linked-files"
        },
        "parent": {
          "__typename": "File",
          "relativePath": "gatsby-remark-copy-linked-files/README.md"
        }
      },
      "npmPackage": {
        "name": "gatsby-remark-copy-linked-files",
        "keywords": [
          "gatsby",
          "gatsby-plugin",
          "prismjs",
          "remark"
        ],
        "lastPublisher": {
          "name": "wardpeet",
          "avatar": "https://gravatar.com/avatar/e574acc76c077a5bac76b07ba89aa9cb"
        }
      }
    },
    "pageContext": {
      "isCreatedByStatefulCreatePages": false,
      "slug": "/packages/gatsby-remark-copy-linked-files/",
      "id": "7f76a2d0-b735-58dc-a685-c8d2be40f8ad",
      "layout": "plugins"
    }
  },
  "query": "query usersMisiekDevGatsbyWwwSrcTemplatesTemplateDocsLocalPackagesJs2742909928(\n  $slug: String!\n) {\n  markdownRemark(fields: {slug: {eq: $slug}}) {\n    html\n    excerpt\n    timeToRead\n    fields {\n      title\n    }\n    ...MarkdownPageFooter\n  }\n  npmPackage(slug: {eq: $slug}) {\n    name\n    keywords\n    lastPublisher {\n      name\n      avatar\n    }\n  }\n}\n\nfragment MarkdownPageFooter on MarkdownRemark {\n  parent {\n    __typename\n    ... on File {\n      relativePath\n    }\n  }\n}\n"
}