{
  "path": "/blog/2018-09-07-gatsby-values/",
  "result": {
    "data": {
      "mdx": {
        "body": "function _extends() { _extends = Object.assign || function (target) { for (var i = 1; i < arguments.length; i++) { var source = arguments[i]; for (var key in source) { if (Object.prototype.hasOwnProperty.call(source, key)) { target[key] = source[key]; } } } return target; }; return _extends.apply(this, arguments); }\n\nfunction _objectWithoutProperties(source, excluded) { if (source == null) return {}; var target = _objectWithoutPropertiesLoose(source, excluded); var key, i; if (Object.getOwnPropertySymbols) { var sourceSymbolKeys = Object.getOwnPropertySymbols(source); for (i = 0; i < sourceSymbolKeys.length; i++) { key = sourceSymbolKeys[i]; if (excluded.indexOf(key) >= 0) continue; if (!Object.prototype.propertyIsEnumerable.call(source, key)) continue; target[key] = source[key]; } } return target; }\n\nfunction _objectWithoutPropertiesLoose(source, excluded) { if (source == null) return {}; var target = {}; var sourceKeys = Object.keys(source); var key, i; for (i = 0; i < sourceKeys.length; i++) { key = sourceKeys[i]; if (excluded.indexOf(key) >= 0) continue; target[key] = source[key]; } return target; }\n\n/* @jsx mdx */\nvar _frontmatter = {\n  \"title\": \"What kind of company will we be? A look at Gatsby’s mission and values.\",\n  \"author\": \"Jason Lengstorf\",\n  \"date\": \"2018-09-07T00:00:00.000Z\",\n  \"image\": \"images/values-whiteboard.jpg\",\n  \"showImageInArticle\": false,\n  \"tags\": [\"gatsby-inc\"]\n};\n\nvar makeShortcode = function makeShortcode(name) {\n  return function MDXDefaultShortcode(props) {\n    console.warn(\"Component \" + name + \" was not imported, exported, or provided by MDXProvider as global scope\");\n    return mdx(\"div\", props);\n  };\n};\n\nvar layoutProps = {\n  _frontmatter: _frontmatter\n};\nvar MDXLayout = \"wrapper\";\nreturn function MDXContent(_ref) {\n  var components = _ref.components,\n      props = _objectWithoutProperties(_ref, [\"components\"]);\n\n  return mdx(MDXLayout, _extends({}, layoutProps, props, {\n    components: components,\n    mdxType: \"MDXLayout\"\n  }), mdx(\"p\", null, \"Most of the Gatsby \", mdx(\"a\", _extends({\n    parentName: \"p\"\n  }, {\n    \"href\": \"https://www.gatsbyjs.com/about/\"\n  }), \"Inkteam\"), \" was together in Portland last week for our latest team onsite, which we lovingly refer to as \\u201CGatsby Gatherings\\u201D. The team assembles every few months to discuss pressing needs, our company\\u2019s direction, and our roadmap.\"), mdx(\"p\", null, \"This was our third Gathering, and it marked the first time when we weren\\u2019t in the midst of a major push (our first Gathering was centered around understanding how the Inkteam would actually function; the second around \", mdx(\"a\", _extends({\n    parentName: \"p\"\n  }, {\n    \"href\": \"/blog/2018-05-24-launching-new-gatsby-company/\"\n  }), \"officially launching the company\"), \").\"), mdx(\"p\", null, \"But this time, with \", mdx(\"a\", _extends({\n    parentName: \"p\"\n  }, {\n    \"href\": \"https://github.com/gatsbyjs/gatsby/blob/master/packages/gatsby/CHANGELOG.md#200-rc0-2018-08-21\"\n  }), \"the v2 release candidate launching last Tuesday\"), \" and \", mdx(\"a\", _extends({\n    parentName: \"p\"\n  }, {\n    \"href\": \"/blog/2018-07-17-announcing-gatsby-preview/\"\n  }), \"Gatsby Preview in alpha\"), \", we had a chance to step back from immediate needs and start looking at the bigger picture: \", mdx(\"strong\", {\n    parentName: \"p\"\n  }, \"what does Gatsby Inc. stand for? What are our goals and values?\")), mdx(\"p\", null, \"This has been a \", mdx(\"em\", {\n    parentName: \"p\"\n  }, \"huge\"), \" \", mdx(\"inlineCode\", {\n    parentName: \"p\"\n  }, \"TODO\"), \" on our list since the very beginning, so we spent a full day thinking through this, writing down our ideas, and discussing what kind of company we want to be.\"), mdx(\"p\", null, \"So last week, given the opportunity to spend in-person time together and talk about it, we tackled the existential questions behind Gatsby Inc.\"), mdx(\"p\", null, \"In this post, we\\u2019ll break down the process we followed, what we came up with, and how these decisions will impact Gatsby moving forward.\"), mdx(\"h2\", {\n    \"id\": \"the-process-of-defining-company-values\"\n  }, mdx(\"a\", _extends({\n    parentName: \"h2\"\n  }, {\n    \"href\": \"#the-process-of-defining-company-values\",\n    \"aria-label\": \"the process of defining company values permalink\",\n    \"className\": \"anchor\"\n  }), mdx(\"svg\", _extends({\n    parentName: \"a\"\n  }, {\n    \"aria-hidden\": \"true\",\n    \"focusable\": \"false\",\n    \"height\": \"16\",\n    \"version\": \"1.1\",\n    \"viewBox\": \"0 0 16 16\",\n    \"width\": \"16\"\n  }), mdx(\"path\", _extends({\n    parentName: \"svg\"\n  }, {\n    \"fillRule\": \"evenodd\",\n    \"d\": \"M4 9h1v1H4c-1.5 0-3-1.69-3-3.5S2.55 3 4 3h4c1.45 0 3 1.69 3 3.5 0 1.41-.91 2.72-2 3.25V8.59c.58-.45 1-1.27 1-2.09C10 5.22 8.98 4 8 4H4c-.98 0-2 1.22-2 2.5S3 9 4 9zm9-3h-1v1h1c1 0 2 1.22 2 2.5S13.98 12 13 12H9c-.98 0-2-1.22-2-2.5 0-.83.42-1.64 1-2.09V6.25c-1.09.53-2 1.84-2 3.25C6 11.31 7.55 13 9 13h4c1.45 0 3-1.69 3-3.5S14.5 6 13 6z\"\n  })))), \"The process of defining company values\"), mdx(\"p\", null, \"Gatsby is a distributed team, which means that on most days we only interact with contributors and team members through Slack and GitHub messages. And with team members everywhere from San Francisco to Chiang Mai, getting the whole team on extended video calls to discuss philosophical questions is extremely difficult.\"), mdx(\"figure\", null, \"\\n  \", mdx(\"span\", _extends({\n    parentName: \"figure\"\n  }, {\n    \"className\": \"gatsby-resp-image-wrapper\",\n    \"style\": {\n      \"position\": \"relative\",\n      \"display\": \"block\",\n      \"marginLeft\": \"auto\",\n      \"marginRight\": \"auto\",\n      \"maxWidth\": \"786px\"\n    }\n  }), \"\\n      \", mdx(\"a\", _extends({\n    parentName: \"span\"\n  }, {\n    \"className\": \"gatsby-resp-image-link\",\n    \"href\": \"/static/5e872856cf114902bea2b3c48b568af7/d7d8f/team-discussion.jpg\",\n    \"style\": {\n      \"display\": \"block\"\n    },\n    \"target\": \"_blank\",\n    \"rel\": [\"noopener\"]\n  }), \"\\n    \", mdx(\"span\", _extends({\n    parentName: \"a\"\n  }, {\n    \"className\": \"gatsby-resp-image-background-image\",\n    \"style\": {\n      \"paddingBottom\": \"55.00000000000001%\",\n      \"position\": \"relative\",\n      \"bottom\": \"0\",\n      \"left\": \"0\",\n      \"backgroundImage\": \"url('data:image/jpeg;base64,/9j/2wBDABALDA4MChAODQ4SERATGCgaGBYWGDEjJR0oOjM9PDkzODdASFxOQERXRTc4UG1RV19iZ2hnPk1xeXBkeFxlZ2P/2wBDARESEhgVGC8aGi9jQjhCY2NjY2NjY2NjY2NjY2NjY2NjY2NjY2NjY2NjY2NjY2NjY2NjY2NjY2NjY2NjY2NjY2P/wgARCAALABQDASIAAhEBAxEB/8QAGAAAAwEBAAAAAAAAAAAAAAAAAAIEAQX/xAAVAQEBAAAAAAAAAAAAAAAAAAABA//aAAwDAQACEAMQAAABSiLR6QpSP//EABsQAAICAwEAAAAAAAAAAAAAAAABAgMREjFC/9oACAEBAAEFAlYSuRF5PKb24f/EABcRAQADAAAAAAAAAAAAAAAAAAABAhL/2gAIAQMBAT8Bymz/xAAWEQEBAQAAAAAAAAAAAAAAAAAAEUH/2gAIAQIBAT8B1H//xAAaEAACAgMAAAAAAAAAAAAAAAAAAREhAjFR/9oACAEBAAY/Ar7BGhtGYij/xAAbEAEAAgMBAQAAAAAAAAAAAAABABEhMUFRof/aAAgBAQABPyHIeFHA43A5F4gs3Gtm/sq6YF3P/9oADAMBAAIAAwAAABBf/wD/xAAYEQEBAAMAAAAAAAAAAAAAAAABABEhQf/aAAgBAwEBPxBIb6WFS//EABYRAQEBAAAAAAAAAAAAAAAAAAEAEf/aAAgBAgEBPxAVwQMv/8QAHBABAAMAAwEBAAAAAAAAAAAAAQARITFBUWGB/9oACAEBAAE/EHXCXSHRp+1GLfYF4GzicOM9eARCLo2fNCOV9G72uAO2JH1n/9k=')\",\n      \"backgroundSize\": \"cover\",\n      \"display\": \"block\"\n    }\n  })), \"\\n  \", mdx(\"img\", _extends({\n    parentName: \"a\"\n  }, {\n    \"className\": \"gatsby-resp-image-image\",\n    \"alt\": \"The Gatsby team gathered around a whiteboard.\",\n    \"title\": \"The Gatsby team gathered around a whiteboard.\",\n    \"src\": \"/static/5e872856cf114902bea2b3c48b568af7/a022f/team-discussion.jpg\",\n    \"srcSet\": [\"/static/5e872856cf114902bea2b3c48b568af7/28bf1/team-discussion.jpg 197w\", \"/static/5e872856cf114902bea2b3c48b568af7/afe26/team-discussion.jpg 393w\", \"/static/5e872856cf114902bea2b3c48b568af7/a022f/team-discussion.jpg 786w\", \"/static/5e872856cf114902bea2b3c48b568af7/6ff56/team-discussion.jpg 1179w\", \"/static/5e872856cf114902bea2b3c48b568af7/b5562/team-discussion.jpg 1572w\", \"/static/5e872856cf114902bea2b3c48b568af7/d7d8f/team-discussion.jpg 2400w\"],\n    \"sizes\": \"(max-width: 786px) 100vw, 786px\",\n    \"loading\": \"lazy\"\n  })), \"\\n  \"), \"\\n    \"), \"\\n  \", mdx(\"figcaption\", {\n    parentName: \"figure\"\n  }, \"\\n    The Inkteam in Portland, Oregon for a Gatsby Gathering. Photo:\\n    \", mdx(\"a\", _extends({\n    parentName: \"figcaption\"\n  }, {\n    \"href\": \"https://www.houseofschaab.photography/\"\n  }), \"Danielle Schaab\"), \"\\n  \")), mdx(\"p\", null, \"We took full advantage of being in the same room with each other to dig into these more nuanced discussions, which started a couple months ago when \", mdx(\"a\", _extends({\n    parentName: \"p\"\n  }, {\n    \"href\": \"https://twitter.com/shannonb_ux\"\n  }), \"Shannon\"), \" asked, \\u201CDo we have any company values?\\u201D\"), mdx(\"h3\", {\n    \"id\": \"step-1-anonymously-collect-ideas\"\n  }, mdx(\"a\", _extends({\n    parentName: \"h3\"\n  }, {\n    \"href\": \"#step-1-anonymously-collect-ideas\",\n    \"aria-label\": \"step 1 anonymously collect ideas permalink\",\n    \"className\": \"anchor\"\n  }), mdx(\"svg\", _extends({\n    parentName: \"a\"\n  }, {\n    \"aria-hidden\": \"true\",\n    \"focusable\": \"false\",\n    \"height\": \"16\",\n    \"version\": \"1.1\",\n    \"viewBox\": \"0 0 16 16\",\n    \"width\": \"16\"\n  }), mdx(\"path\", _extends({\n    parentName: \"svg\"\n  }, {\n    \"fillRule\": \"evenodd\",\n    \"d\": \"M4 9h1v1H4c-1.5 0-3-1.69-3-3.5S2.55 3 4 3h4c1.45 0 3 1.69 3 3.5 0 1.41-.91 2.72-2 3.25V8.59c.58-.45 1-1.27 1-2.09C10 5.22 8.98 4 8 4H4c-.98 0-2 1.22-2 2.5S3 9 4 9zm9-3h-1v1h1c1 0 2 1.22 2 2.5S13.98 12 13 12H9c-.98 0-2-1.22-2-2.5 0-.83.42-1.64 1-2.09V6.25c-1.09.53-2 1.84-2 3.25C6 11.31 7.55 13 9 13h4c1.45 0 3-1.69 3-3.5S14.5 6 13 6z\"\n  })))), \"Step 1: Anonymously collect ideas\"), mdx(\"p\", null, mdx(\"a\", _extends({\n    parentName: \"p\"\n  }, {\n    \"href\": \"https://twitter.com/calcsam\"\n  }), \"Sam\"), \" led the effort by creating a Google Form to collect anonymous feedback on what Gatsby\\u2019s mission and values should be. We sent this form around to everyone and allowed a couple weeks for everyone to get their ideas in.\"), mdx(\"h3\", {\n    \"id\": \"step-2-condense-anonymous-ideas-into-themes\"\n  }, mdx(\"a\", _extends({\n    parentName: \"h3\"\n  }, {\n    \"href\": \"#step-2-condense-anonymous-ideas-into-themes\",\n    \"aria-label\": \"step 2 condense anonymous ideas into themes permalink\",\n    \"className\": \"anchor\"\n  }), mdx(\"svg\", _extends({\n    parentName: \"a\"\n  }, {\n    \"aria-hidden\": \"true\",\n    \"focusable\": \"false\",\n    \"height\": \"16\",\n    \"version\": \"1.1\",\n    \"viewBox\": \"0 0 16 16\",\n    \"width\": \"16\"\n  }), mdx(\"path\", _extends({\n    parentName: \"svg\"\n  }, {\n    \"fillRule\": \"evenodd\",\n    \"d\": \"M4 9h1v1H4c-1.5 0-3-1.69-3-3.5S2.55 3 4 3h4c1.45 0 3 1.69 3 3.5 0 1.41-.91 2.72-2 3.25V8.59c.58-.45 1-1.27 1-2.09C10 5.22 8.98 4 8 4H4c-.98 0-2 1.22-2 2.5S3 9 4 9zm9-3h-1v1h1c1 0 2 1.22 2 2.5S13.98 12 13 12H9c-.98 0-2-1.22-2-2.5 0-.83.42-1.64 1-2.09V6.25c-1.09.53-2 1.84-2 3.25C6 11.31 7.55 13 9 13h4c1.45 0 3-1.69 3-3.5S14.5 6 13 6z\"\n  })))), \"Step 2: Condense anonymous ideas into themes\"), mdx(\"p\", null, \"Once we had all the anonymous ideas collected, Sam condensed them into common themes.\"), mdx(\"h3\", {\n    \"id\": \"step-3-discuss-the-themes-in-person\"\n  }, mdx(\"a\", _extends({\n    parentName: \"h3\"\n  }, {\n    \"href\": \"#step-3-discuss-the-themes-in-person\",\n    \"aria-label\": \"step 3 discuss the themes in person permalink\",\n    \"className\": \"anchor\"\n  }), mdx(\"svg\", _extends({\n    parentName: \"a\"\n  }, {\n    \"aria-hidden\": \"true\",\n    \"focusable\": \"false\",\n    \"height\": \"16\",\n    \"version\": \"1.1\",\n    \"viewBox\": \"0 0 16 16\",\n    \"width\": \"16\"\n  }), mdx(\"path\", _extends({\n    parentName: \"svg\"\n  }, {\n    \"fillRule\": \"evenodd\",\n    \"d\": \"M4 9h1v1H4c-1.5 0-3-1.69-3-3.5S2.55 3 4 3h4c1.45 0 3 1.69 3 3.5 0 1.41-.91 2.72-2 3.25V8.59c.58-.45 1-1.27 1-2.09C10 5.22 8.98 4 8 4H4c-.98 0-2 1.22-2 2.5S3 9 4 9zm9-3h-1v1h1c1 0 2 1.22 2 2.5S13.98 12 13 12H9c-.98 0-2-1.22-2-2.5 0-.83.42-1.64 1-2.09V6.25c-1.09.53-2 1.84-2 3.25C6 11.31 7.55 13 9 13h4c1.45 0 3-1.69 3-3.5S14.5 6 13 6z\"\n  })))), \"Step 3: Discuss the themes in person\"), mdx(\"p\", null, \"While we were all together, Sam went through the themes with all of us and we wrote them out on a whiteboard. This helped all of us get back into the context of what we\\u2019d written down before, and what the team collectively values.\"), mdx(\"figure\", null, \"\\n  \", mdx(\"span\", _extends({\n    parentName: \"figure\"\n  }, {\n    \"className\": \"gatsby-resp-image-wrapper\",\n    \"style\": {\n      \"position\": \"relative\",\n      \"display\": \"block\",\n      \"marginLeft\": \"auto\",\n      \"marginRight\": \"auto\",\n      \"maxWidth\": \"786px\"\n    }\n  }), \"\\n      \", mdx(\"a\", _extends({\n    parentName: \"span\"\n  }, {\n    \"className\": \"gatsby-resp-image-link\",\n    \"href\": \"/static/98f346f7cca67167160d1ab58a8e86ef/d7d8f/kurt-sticky-note.jpg\",\n    \"style\": {\n      \"display\": \"block\"\n    },\n    \"target\": \"_blank\",\n    \"rel\": [\"noopener\"]\n  }), \"\\n    \", mdx(\"span\", _extends({\n    parentName: \"a\"\n  }, {\n    \"className\": \"gatsby-resp-image-background-image\",\n    \"style\": {\n      \"paddingBottom\": \"55.00000000000001%\",\n      \"position\": \"relative\",\n      \"bottom\": \"0\",\n      \"left\": \"0\",\n      \"backgroundImage\": \"url('data:image/jpeg;base64,/9j/2wBDABALDA4MChAODQ4SERATGCgaGBYWGDEjJR0oOjM9PDkzODdASFxOQERXRTc4UG1RV19iZ2hnPk1xeXBkeFxlZ2P/2wBDARESEhgVGC8aGi9jQjhCY2NjY2NjY2NjY2NjY2NjY2NjY2NjY2NjY2NjY2NjY2NjY2NjY2NjY2NjY2NjY2NjY2P/wgARCAALABQDASIAAhEBAxEB/8QAGAAAAwEBAAAAAAAAAAAAAAAAAAIFAwT/xAAWAQEBAQAAAAAAAAAAAAAAAAADAQL/2gAMAwEAAhADEAAAAUx5XNKRPJv/xAAZEAEBAAMBAAAAAAAAAAAAAAACAQMSMTP/2gAIAQEAAQUCVlOpkxEoP0XZz//EABcRAQADAAAAAAAAAAAAAAAAAAABEiH/2gAIAQMBAT8BjVX/xAAVEQEBAAAAAAAAAAAAAAAAAAAQEf/aAAgBAgEBPwGH/8QAGBABAAMBAAAAAAAAAAAAAAAAAQAQIVL/2gAIAQEABj8CSPUNpr//xAAcEAEAAgEFAAAAAAAAAAAAAAABABEhMUFRgaH/2gAIAQEAAT8huhtzDQwDItkQrwh3noiQU1P/2gAMAwEAAgADAAAAEMf/AP/EABYRAQEBAAAAAAAAAAAAAAAAAAARAf/aAAgBAwEBPxDFIf/EABYRAQEBAAAAAAAAAAAAAAAAAAEAEf/aAAgBAgEBPxAwWN//xAAcEAEAAgIDAQAAAAAAAAAAAAABABEhMUFRcbH/2gAIAQEAAT8QQZNEpC9c2cL1nyEXpaB+xyAUhZkLpTAVBXDP/9k=')\",\n      \"backgroundSize\": \"cover\",\n      \"display\": \"block\"\n    }\n  })), \"\\n  \", mdx(\"img\", _extends({\n    parentName: \"a\"\n  }, {\n    \"className\": \"gatsby-resp-image-image\",\n    \"alt\": \"Kurt holding a sticky note with “always be open to change” written on it.\",\n    \"title\": \"Kurt holding a sticky note with “always be open to change” written on it.\",\n    \"src\": \"/static/98f346f7cca67167160d1ab58a8e86ef/a022f/kurt-sticky-note.jpg\",\n    \"srcSet\": [\"/static/98f346f7cca67167160d1ab58a8e86ef/28bf1/kurt-sticky-note.jpg 197w\", \"/static/98f346f7cca67167160d1ab58a8e86ef/afe26/kurt-sticky-note.jpg 393w\", \"/static/98f346f7cca67167160d1ab58a8e86ef/a022f/kurt-sticky-note.jpg 786w\", \"/static/98f346f7cca67167160d1ab58a8e86ef/6ff56/kurt-sticky-note.jpg 1179w\", \"/static/98f346f7cca67167160d1ab58a8e86ef/b5562/kurt-sticky-note.jpg 1572w\", \"/static/98f346f7cca67167160d1ab58a8e86ef/d7d8f/kurt-sticky-note.jpg 2400w\"],\n    \"sizes\": \"(max-width: 786px) 100vw, 786px\",\n    \"loading\": \"lazy\"\n  })), \"\\n  \"), \"\\n    \"), \"\\n  \", mdx(\"figcaption\", {\n    parentName: \"figure\"\n  }, \"\\n    Kurt writing down really good ideas on a sticky note. Photo:\\n    \", mdx(\"a\", _extends({\n    parentName: \"figcaption\"\n  }, {\n    \"href\": \"https://www.houseofschaab.photography/\"\n  }), \"Danielle Schaab\"), \"\\n  \")), mdx(\"h3\", {\n    \"id\": \"step-4-capture-additional-ideas-on-sticky-notes\"\n  }, mdx(\"a\", _extends({\n    parentName: \"h3\"\n  }, {\n    \"href\": \"#step-4-capture-additional-ideas-on-sticky-notes\",\n    \"aria-label\": \"step 4 capture additional ideas on sticky notes permalink\",\n    \"className\": \"anchor\"\n  }), mdx(\"svg\", _extends({\n    parentName: \"a\"\n  }, {\n    \"aria-hidden\": \"true\",\n    \"focusable\": \"false\",\n    \"height\": \"16\",\n    \"version\": \"1.1\",\n    \"viewBox\": \"0 0 16 16\",\n    \"width\": \"16\"\n  }), mdx(\"path\", _extends({\n    parentName: \"svg\"\n  }, {\n    \"fillRule\": \"evenodd\",\n    \"d\": \"M4 9h1v1H4c-1.5 0-3-1.69-3-3.5S2.55 3 4 3h4c1.45 0 3 1.69 3 3.5 0 1.41-.91 2.72-2 3.25V8.59c.58-.45 1-1.27 1-2.09C10 5.22 8.98 4 8 4H4c-.98 0-2 1.22-2 2.5S3 9 4 9zm9-3h-1v1h1c1 0 2 1.22 2 2.5S13.98 12 13 12H9c-.98 0-2-1.22-2-2.5 0-.83.42-1.64 1-2.09V6.25c-1.09.53-2 1.84-2 3.25C6 11.31 7.55 13 9 13h4c1.45 0 3-1.69 3-3.5S14.5 6 13 6z\"\n  })))), \"Step 4: Capture additional ideas on sticky notes\"), mdx(\"p\", null, \"Once we all had context, we distributed sticky notes and markers, then set a timer for 15 minutes to allow everyone to add any additional ideas, values, or themes that weren\\u2019t covered in the original document.\"), mdx(\"h3\", {\n    \"id\": \"step-5-group-similar-ideas-and-identify-the-core-values\"\n  }, mdx(\"a\", _extends({\n    parentName: \"h3\"\n  }, {\n    \"href\": \"#step-5-group-similar-ideas-and-identify-the-core-values\",\n    \"aria-label\": \"step 5 group similar ideas and identify the core values permalink\",\n    \"className\": \"anchor\"\n  }), mdx(\"svg\", _extends({\n    parentName: \"a\"\n  }, {\n    \"aria-hidden\": \"true\",\n    \"focusable\": \"false\",\n    \"height\": \"16\",\n    \"version\": \"1.1\",\n    \"viewBox\": \"0 0 16 16\",\n    \"width\": \"16\"\n  }), mdx(\"path\", _extends({\n    parentName: \"svg\"\n  }, {\n    \"fillRule\": \"evenodd\",\n    \"d\": \"M4 9h1v1H4c-1.5 0-3-1.69-3-3.5S2.55 3 4 3h4c1.45 0 3 1.69 3 3.5 0 1.41-.91 2.72-2 3.25V8.59c.58-.45 1-1.27 1-2.09C10 5.22 8.98 4 8 4H4c-.98 0-2 1.22-2 2.5S3 9 4 9zm9-3h-1v1h1c1 0 2 1.22 2 2.5S13.98 12 13 12H9c-.98 0-2-1.22-2-2.5 0-.83.42-1.64 1-2.09V6.25c-1.09.53-2 1.84-2 3.25C6 11.31 7.55 13 9 13h4c1.45 0 3-1.69 3-3.5S14.5 6 13 6z\"\n  })))), \"Step 5: Group similar ideas and identify the core values\"), mdx(\"p\", null, \"With everyone\\u2019s ideas on the board, we started grouping. \", mdx(\"a\", _extends({\n    parentName: \"p\"\n  }, {\n    \"href\": \"https://twitter.com/marisamorby\"\n  }), \"Marisa\"), \" and I looked for common threads in the ideas on the whiteboard and started to condense them down into a set of core values.\"), mdx(\"figure\", null, \"\\n  \", mdx(\"span\", _extends({\n    parentName: \"figure\"\n  }, {\n    \"className\": \"gatsby-resp-image-wrapper\",\n    \"style\": {\n      \"position\": \"relative\",\n      \"display\": \"block\",\n      \"marginLeft\": \"auto\",\n      \"marginRight\": \"auto\",\n      \"maxWidth\": \"786px\"\n    }\n  }), \"\\n      \", mdx(\"a\", _extends({\n    parentName: \"span\"\n  }, {\n    \"className\": \"gatsby-resp-image-link\",\n    \"href\": \"/static/0fb8ce7959ce96d707cc3a274c905dd8/d7d8f/values-whiteboard.jpg\",\n    \"style\": {\n      \"display\": \"block\"\n    },\n    \"target\": \"_blank\",\n    \"rel\": [\"noopener\"]\n  }), \"\\n    \", mdx(\"span\", _extends({\n    parentName: \"a\"\n  }, {\n    \"className\": \"gatsby-resp-image-background-image\",\n    \"style\": {\n      \"paddingBottom\": \"55.00000000000001%\",\n      \"position\": \"relative\",\n      \"bottom\": \"0\",\n      \"left\": \"0\",\n      \"backgroundImage\": \"url('data:image/jpeg;base64,/9j/2wBDABALDA4MChAODQ4SERATGCgaGBYWGDEjJR0oOjM9PDkzODdASFxOQERXRTc4UG1RV19iZ2hnPk1xeXBkeFxlZ2P/2wBDARESEhgVGC8aGi9jQjhCY2NjY2NjY2NjY2NjY2NjY2NjY2NjY2NjY2NjY2NjY2NjY2NjY2NjY2NjY2NjY2NjY2P/wgARCAALABQDASIAAhEBAxEB/8QAGQAAAgMBAAAAAAAAAAAAAAAAAAIBAwQF/8QAFAEBAAAAAAAAAAAAAAAAAAAAAf/aAAwDAQACEAMQAAAB0vUwQc8T/8QAGxAAAgIDAQAAAAAAAAAAAAAAAQIDESExMkP/2gAIAQEAAQUCm58UktH1eAaH/8QAFhEBAQEAAAAAAAAAAAAAAAAAAAES/9oACAEDAQE/AWa//8QAFREBAQAAAAAAAAAAAAAAAAAAABH/2gAIAQIBAT8BV//EABcQAQEBAQAAAAAAAAAAAAAAAAEAgZH/2gAIAQEABj8ChYbkbF//xAAaEAEAAgMBAAAAAAAAAAAAAAABABEhMVFB/9oACAEBAAE/IcPJj2C0lNZhMu47y7Cm/kKI1XJ//9oADAMBAAIAAwAAABDfz//EABcRAAMBAAAAAAAAAAAAAAAAAAABEXH/2gAIAQMBAT8QlWjsf//EABYRAQEBAAAAAAAAAAAAAAAAAAEAEf/aAAgBAgEBPxDQg3//xAAaEAEBAQEBAQEAAAAAAAAAAAABEQAhMVFh/9oACAEBAAE/EEiqE1XHzmGQ6QNmhgmh8MhcMAp4YbVLSfrmrAccb//Z')\",\n      \"backgroundSize\": \"cover\",\n      \"display\": \"block\"\n    }\n  })), \"\\n  \", mdx(\"img\", _extends({\n    parentName: \"a\"\n  }, {\n    \"className\": \"gatsby-resp-image-image\",\n    \"alt\": \"Kyle, Linda, and Marisa adding and grouping ideas on the whiteboard.\",\n    \"title\": \"Kyle, Linda, and Marisa adding and grouping ideas on the whiteboard.\",\n    \"src\": \"/static/0fb8ce7959ce96d707cc3a274c905dd8/a022f/values-whiteboard.jpg\",\n    \"srcSet\": [\"/static/0fb8ce7959ce96d707cc3a274c905dd8/28bf1/values-whiteboard.jpg 197w\", \"/static/0fb8ce7959ce96d707cc3a274c905dd8/afe26/values-whiteboard.jpg 393w\", \"/static/0fb8ce7959ce96d707cc3a274c905dd8/a022f/values-whiteboard.jpg 786w\", \"/static/0fb8ce7959ce96d707cc3a274c905dd8/6ff56/values-whiteboard.jpg 1179w\", \"/static/0fb8ce7959ce96d707cc3a274c905dd8/b5562/values-whiteboard.jpg 1572w\", \"/static/0fb8ce7959ce96d707cc3a274c905dd8/d7d8f/values-whiteboard.jpg 2400w\"],\n    \"sizes\": \"(max-width: 786px) 100vw, 786px\",\n    \"loading\": \"lazy\"\n  })), \"\\n  \"), \"\\n    \"), \"\\n  \", mdx(\"figcaption\", {\n    parentName: \"figure\"\n  }, \"\\n    Kyle, Linda, and Marisa adding and grouping ideas on the whiteboard. Photo:\\n    \", mdx(\"a\", _extends({\n    parentName: \"figcaption\"\n  }, {\n    \"href\": \"https://www.houseofschaab.photography/\"\n  }), \"Danielle Schaab\"), \"\\n  \")), mdx(\"p\", null, \"As we wrote these out, we discussed them with the whole team to make sure we weren\\u2019t oversimplifying or losing the message behind anyone\\u2019s ideas.\"), mdx(\"p\", null, \"At the end of the exercise, we\\u2019d extracted 8 shared core values, all of which the team is fully aligned on and deeply committed to.\"), mdx(\"blockquote\", {\n    className: \"twitter-tweet\",\n    \"data-lang\": \"en\"\n  }, mdx(\"p\", {\n    lang: \"en\",\n    dir: \"ltr\"\n  }, \"What we're doing at\", \" \", mdx(\"a\", {\n    href: \"https://twitter.com/gatsbyjs?ref_src=twsrc%5Etfw\"\n  }, \"@gatsbyjs\"), \" \", \"this week: writing down what kind of company we want to be.\", \" \", mdx(\"a\", {\n    href: \"https://t.co/N0SRaJXILS\"\n  }, \"pic.twitter.com/N0SRaJXILS\")), \"\\u2014 Jason Lengstorf (@jlengstorf)\", \" \", mdx(\"a\", {\n    href: \"https://twitter.com/jlengstorf/status/1032319257298628608?ref_src=twsrc%5Etfw\"\n  }, \"August 22, 2018\")), mdx(\"h2\", {\n    \"id\": \"what-we-learned--gatsbys-core-values\"\n  }, mdx(\"a\", _extends({\n    parentName: \"h2\"\n  }, {\n    \"href\": \"#what-we-learned--gatsbys-core-values\",\n    \"aria-label\": \"what we learned  gatsbys core values permalink\",\n    \"className\": \"anchor\"\n  }), mdx(\"svg\", _extends({\n    parentName: \"a\"\n  }, {\n    \"aria-hidden\": \"true\",\n    \"focusable\": \"false\",\n    \"height\": \"16\",\n    \"version\": \"1.1\",\n    \"viewBox\": \"0 0 16 16\",\n    \"width\": \"16\"\n  }), mdx(\"path\", _extends({\n    parentName: \"svg\"\n  }, {\n    \"fillRule\": \"evenodd\",\n    \"d\": \"M4 9h1v1H4c-1.5 0-3-1.69-3-3.5S2.55 3 4 3h4c1.45 0 3 1.69 3 3.5 0 1.41-.91 2.72-2 3.25V8.59c.58-.45 1-1.27 1-2.09C10 5.22 8.98 4 8 4H4c-.98 0-2 1.22-2 2.5S3 9 4 9zm9-3h-1v1h1c1 0 2 1.22 2 2.5S13.98 12 13 12H9c-.98 0-2-1.22-2-2.5 0-.83.42-1.64 1-2.09V6.25c-1.09.53-2 1.84-2 3.25C6 11.31 7.55 13 9 13h4c1.45 0 3-1.69 3-3.5S14.5 6 13 6z\"\n  })))), \"What we learned \\u2014 Gatsby\\u2019s core values\"), mdx(\"p\", null, \"With our themes identified, we needed to polish our notes up into clear company values. Here\\u2019s what we settled on.\"), mdx(\"h3\", {\n    \"id\": \"do-the-right-thing-when-no-one-is-looking\"\n  }, mdx(\"a\", _extends({\n    parentName: \"h3\"\n  }, {\n    \"href\": \"#do-the-right-thing-when-no-one-is-looking\",\n    \"aria-label\": \"do the right thing when no one is looking permalink\",\n    \"className\": \"anchor\"\n  }), mdx(\"svg\", _extends({\n    parentName: \"a\"\n  }, {\n    \"aria-hidden\": \"true\",\n    \"focusable\": \"false\",\n    \"height\": \"16\",\n    \"version\": \"1.1\",\n    \"viewBox\": \"0 0 16 16\",\n    \"width\": \"16\"\n  }), mdx(\"path\", _extends({\n    parentName: \"svg\"\n  }, {\n    \"fillRule\": \"evenodd\",\n    \"d\": \"M4 9h1v1H4c-1.5 0-3-1.69-3-3.5S2.55 3 4 3h4c1.45 0 3 1.69 3 3.5 0 1.41-.91 2.72-2 3.25V8.59c.58-.45 1-1.27 1-2.09C10 5.22 8.98 4 8 4H4c-.98 0-2 1.22-2 2.5S3 9 4 9zm9-3h-1v1h1c1 0 2 1.22 2 2.5S13.98 12 13 12H9c-.98 0-2-1.22-2-2.5 0-.83.42-1.64 1-2.09V6.25c-1.09.53-2 1.84-2 3.25C6 11.31 7.55 13 9 13h4c1.45 0 3-1.69 3-3.5S14.5 6 13 6z\"\n  })))), \"Do the right thing when no one is looking\"), mdx(\"p\", null, \"Companies live or die by the trust they build. Gatsby is an open source product, and that means we need to earn and maintain trust from our internal team, our larger community of contributors (and the open source community at large), as well as from our clients and customers.\"), mdx(\"p\", null, \"To earn that trust, we need to be deeply committed to always doing the right thing \", mdx(\"em\", {\n    parentName: \"p\"\n  }, \"for the sake of doing the right thing\"), \".\"), mdx(\"p\", null, mdx(\"strong\", {\n    parentName: \"p\"\n  }, \"Our integrity \\u2014 both professional and personal \\u2014 is the foundation for everything else.\")), mdx(\"h3\", {\n    \"id\": \"work-in-the-open\"\n  }, mdx(\"a\", _extends({\n    parentName: \"h3\"\n  }, {\n    \"href\": \"#work-in-the-open\",\n    \"aria-label\": \"work in the open permalink\",\n    \"className\": \"anchor\"\n  }), mdx(\"svg\", _extends({\n    parentName: \"a\"\n  }, {\n    \"aria-hidden\": \"true\",\n    \"focusable\": \"false\",\n    \"height\": \"16\",\n    \"version\": \"1.1\",\n    \"viewBox\": \"0 0 16 16\",\n    \"width\": \"16\"\n  }), mdx(\"path\", _extends({\n    parentName: \"svg\"\n  }, {\n    \"fillRule\": \"evenodd\",\n    \"d\": \"M4 9h1v1H4c-1.5 0-3-1.69-3-3.5S2.55 3 4 3h4c1.45 0 3 1.69 3 3.5 0 1.41-.91 2.72-2 3.25V8.59c.58-.45 1-1.27 1-2.09C10 5.22 8.98 4 8 4H4c-.98 0-2 1.22-2 2.5S3 9 4 9zm9-3h-1v1h1c1 0 2 1.22 2 2.5S13.98 12 13 12H9c-.98 0-2-1.22-2-2.5 0-.83.42-1.64 1-2.09V6.25c-1.09.53-2 1.84-2 3.25C6 11.31 7.55 13 9 13h4c1.45 0 3-1.69 3-3.5S14.5 6 13 6z\"\n  })))), \"Work in the open\"), mdx(\"p\", null, \"Open source is at the core of Gatsby\\u2019s success, and one of the central tenets of open source is that things are done in the open and without smoke, mirrors, pomp, circumstance, cloaks, or daggers.\"), mdx(\"p\", null, \"Gatsby\\u2019s competitive advantage is the strength of its community and ecosystem, and we\\u2019re convinced that the right path forward is to continue working in the open, sharing our plans, ideas, struggles, and successes as transparently as possible.\"), mdx(\"p\", null, \"To put it plainly: \", mdx(\"strong\", {\n    parentName: \"p\"\n  }, \"unless it\\u2019s a critical competitive advantage, we\\u2019ll put it in public.\")), mdx(\"h3\", {\n    \"id\": \"set-and-manage-clear-expectations\"\n  }, mdx(\"a\", _extends({\n    parentName: \"h3\"\n  }, {\n    \"href\": \"#set-and-manage-clear-expectations\",\n    \"aria-label\": \"set and manage clear expectations permalink\",\n    \"className\": \"anchor\"\n  }), mdx(\"svg\", _extends({\n    parentName: \"a\"\n  }, {\n    \"aria-hidden\": \"true\",\n    \"focusable\": \"false\",\n    \"height\": \"16\",\n    \"version\": \"1.1\",\n    \"viewBox\": \"0 0 16 16\",\n    \"width\": \"16\"\n  }), mdx(\"path\", _extends({\n    parentName: \"svg\"\n  }, {\n    \"fillRule\": \"evenodd\",\n    \"d\": \"M4 9h1v1H4c-1.5 0-3-1.69-3-3.5S2.55 3 4 3h4c1.45 0 3 1.69 3 3.5 0 1.41-.91 2.72-2 3.25V8.59c.58-.45 1-1.27 1-2.09C10 5.22 8.98 4 8 4H4c-.98 0-2 1.22-2 2.5S3 9 4 9zm9-3h-1v1h1c1 0 2 1.22 2 2.5S13.98 12 13 12H9c-.98 0-2-1.22-2-2.5 0-.83.42-1.64 1-2.09V6.25c-1.09.53-2 1.84-2 3.25C6 11.31 7.55 13 9 13h4c1.45 0 3-1.69 3-3.5S14.5 6 13 6z\"\n  })))), \"Set and manage clear expectations\"), mdx(\"p\", null, \"Setting and meeting expectations is the backbone of successful business (and people). It\\u2019s how we show respect, act professionally, and maintain healthy relationships.\"), mdx(\"p\", null, mdx(\"strong\", {\n    parentName: \"p\"\n  }, \"If we say we\\u2019re going to do something, we\\u2019ll do it.\"), \" If we\\u2019re going to miss a deadline, we\\u2019ll tell you \", mdx(\"em\", {\n    parentName: \"p\"\n  }, \"before\"), \" it passes. We\\u2019ll show up to meetings on time \\u2014 and if we\\u2019re going to be late, we\\u2019ll email or text to let you know.\"), mdx(\"p\", null, \"Behind all bad feelings \\u2014 anger, disappointment, frustration, and beyond \\u2014 there\\u2019s almost always a violated expectation. Gatsby is all about creating great experiences and good feelings, and managing expectations is how we make sure we live up to our goals.\"), mdx(\"h3\", {\n    \"id\": \"go-slow-to-go-fast\"\n  }, mdx(\"a\", _extends({\n    parentName: \"h3\"\n  }, {\n    \"href\": \"#go-slow-to-go-fast\",\n    \"aria-label\": \"go slow to go fast permalink\",\n    \"className\": \"anchor\"\n  }), mdx(\"svg\", _extends({\n    parentName: \"a\"\n  }, {\n    \"aria-hidden\": \"true\",\n    \"focusable\": \"false\",\n    \"height\": \"16\",\n    \"version\": \"1.1\",\n    \"viewBox\": \"0 0 16 16\",\n    \"width\": \"16\"\n  }), mdx(\"path\", _extends({\n    parentName: \"svg\"\n  }, {\n    \"fillRule\": \"evenodd\",\n    \"d\": \"M4 9h1v1H4c-1.5 0-3-1.69-3-3.5S2.55 3 4 3h4c1.45 0 3 1.69 3 3.5 0 1.41-.91 2.72-2 3.25V8.59c.58-.45 1-1.27 1-2.09C10 5.22 8.98 4 8 4H4c-.98 0-2 1.22-2 2.5S3 9 4 9zm9-3h-1v1h1c1 0 2 1.22 2 2.5S13.98 12 13 12H9c-.98 0-2-1.22-2-2.5 0-.83.42-1.64 1-2.09V6.25c-1.09.53-2 1.84-2 3.25C6 11.31 7.55 13 9 13h4c1.45 0 3-1.69 3-3.5S14.5 6 13 6z\"\n  })))), \"Go slow to go fast\"), mdx(\"p\", null, \"All projects are planned. The question is whether they\\u2019re planned upfront, or halfway through.\"), mdx(\"p\", null, \"We understand the value of moving quickly and shipping things regularly. We also understand the value in first thinking things through to make sure we\\u2019re moving in the right direction and shipping the right things.\"), mdx(\"p\", null, mdx(\"strong\", {\n    parentName: \"p\"\n  }, \"By taking the time up front to think through our goals and plan appropriately, we will avoid costly mistakes and slowdowns, keep the team and community on the same page, and ultimately move \", mdx(\"em\", {\n    parentName: \"strong\"\n  }, \"much faster\")), \" than if we were charging ahead without thinking things through.\"), mdx(\"h3\", {\n    \"id\": \"always-prioritize-developer-experience-and-user-experience\"\n  }, mdx(\"a\", _extends({\n    parentName: \"h3\"\n  }, {\n    \"href\": \"#always-prioritize-developer-experience-and-user-experience\",\n    \"aria-label\": \"always prioritize developer experience and user experience permalink\",\n    \"className\": \"anchor\"\n  }), mdx(\"svg\", _extends({\n    parentName: \"a\"\n  }, {\n    \"aria-hidden\": \"true\",\n    \"focusable\": \"false\",\n    \"height\": \"16\",\n    \"version\": \"1.1\",\n    \"viewBox\": \"0 0 16 16\",\n    \"width\": \"16\"\n  }), mdx(\"path\", _extends({\n    parentName: \"svg\"\n  }, {\n    \"fillRule\": \"evenodd\",\n    \"d\": \"M4 9h1v1H4c-1.5 0-3-1.69-3-3.5S2.55 3 4 3h4c1.45 0 3 1.69 3 3.5 0 1.41-.91 2.72-2 3.25V8.59c.58-.45 1-1.27 1-2.09C10 5.22 8.98 4 8 4H4c-.98 0-2 1.22-2 2.5S3 9 4 9zm9-3h-1v1h1c1 0 2 1.22 2 2.5S13.98 12 13 12H9c-.98 0-2-1.22-2-2.5 0-.83.42-1.64 1-2.09V6.25c-1.09.53-2 1.84-2 3.25C6 11.31 7.55 13 9 13h4c1.45 0 3-1.69 3-3.5S14.5 6 13 6z\"\n  })))), \"Always prioritize developer experience and user experience\"), mdx(\"p\", null, \"Whenever we make decisions, we will put the experience of the developers using Gatsby and the people who will use the sites generated by Gatsby first. Even if it means extra work to add helpful error messages. Even if it means refactoring a confusing API to be more user friendly.\"), mdx(\"p\", null, mdx(\"strong\", {\n    parentName: \"p\"\n  }, \"Gatsby has built its reputation on being a pleasure to work with, and we\\u2019re dedicated to keeping that true.\")), mdx(\"h3\", {\n    \"id\": \"embrace-growth\"\n  }, mdx(\"a\", _extends({\n    parentName: \"h3\"\n  }, {\n    \"href\": \"#embrace-growth\",\n    \"aria-label\": \"embrace growth permalink\",\n    \"className\": \"anchor\"\n  }), mdx(\"svg\", _extends({\n    parentName: \"a\"\n  }, {\n    \"aria-hidden\": \"true\",\n    \"focusable\": \"false\",\n    \"height\": \"16\",\n    \"version\": \"1.1\",\n    \"viewBox\": \"0 0 16 16\",\n    \"width\": \"16\"\n  }), mdx(\"path\", _extends({\n    parentName: \"svg\"\n  }, {\n    \"fillRule\": \"evenodd\",\n    \"d\": \"M4 9h1v1H4c-1.5 0-3-1.69-3-3.5S2.55 3 4 3h4c1.45 0 3 1.69 3 3.5 0 1.41-.91 2.72-2 3.25V8.59c.58-.45 1-1.27 1-2.09C10 5.22 8.98 4 8 4H4c-.98 0-2 1.22-2 2.5S3 9 4 9zm9-3h-1v1h1c1 0 2 1.22 2 2.5S13.98 12 13 12H9c-.98 0-2-1.22-2-2.5 0-.83.42-1.64 1-2.09V6.25c-1.09.53-2 1.84-2 3.25C6 11.31 7.55 13 9 13h4c1.45 0 3-1.69 3-3.5S14.5 6 13 6z\"\n  })))), \"Embrace growth\"), mdx(\"p\", null, mdx(\"strong\", {\n    parentName: \"p\"\n  }, \"Healthy things grow, and growing things change.\"), \" Gatsby is a fast-growing, cutting edge technology startup, and that means things are in near-constant flux. This means that we\\u2019re regularly up against circumstances that are rapidly evolving.\"), mdx(\"p\", null, \"In order to survive and grow, we need to embrace growth as a healthy, vital process. This means making pragmatic decisions early, delegating when necessary, asking for help when it\\u2019s time, and recognizing how we\\u2019ve always done things isn\\u2019t necessarily what works \", mdx(\"em\", {\n    parentName: \"p\"\n  }, \"today\"), \". (And what works today may very well stop working tomorrow.)\"), mdx(\"p\", null, \"These changes aren\\u2019t a sign that we\\u2019re failing, or that things are wrong. It\\u2019s a sign that the company is thriving.\"), mdx(\"h3\", {\n    \"id\": \"experiment-with-cool-ideas\"\n  }, mdx(\"a\", _extends({\n    parentName: \"h3\"\n  }, {\n    \"href\": \"#experiment-with-cool-ideas\",\n    \"aria-label\": \"experiment with cool ideas permalink\",\n    \"className\": \"anchor\"\n  }), mdx(\"svg\", _extends({\n    parentName: \"a\"\n  }, {\n    \"aria-hidden\": \"true\",\n    \"focusable\": \"false\",\n    \"height\": \"16\",\n    \"version\": \"1.1\",\n    \"viewBox\": \"0 0 16 16\",\n    \"width\": \"16\"\n  }), mdx(\"path\", _extends({\n    parentName: \"svg\"\n  }, {\n    \"fillRule\": \"evenodd\",\n    \"d\": \"M4 9h1v1H4c-1.5 0-3-1.69-3-3.5S2.55 3 4 3h4c1.45 0 3 1.69 3 3.5 0 1.41-.91 2.72-2 3.25V8.59c.58-.45 1-1.27 1-2.09C10 5.22 8.98 4 8 4H4c-.98 0-2 1.22-2 2.5S3 9 4 9zm9-3h-1v1h1c1 0 2 1.22 2 2.5S13.98 12 13 12H9c-.98 0-2-1.22-2-2.5 0-.83.42-1.64 1-2.09V6.25c-1.09.53-2 1.84-2 3.25C6 11.31 7.55 13 9 13h4c1.45 0 3-1.69 3-3.5S14.5 6 13 6z\"\n  })))), \"Experiment with cool ideas\"), mdx(\"p\", null, \"Gatsby began as an experiment with bleeding edge technology. As a product, Gatsby has always aimed to be at the forefront of technological advances.\"), mdx(\"p\", null, \"While we need to stick to our roadmap and make steady progress toward our company goals, \", mdx(\"strong\", {\n    parentName: \"p\"\n  }, \"we will maintain a state of excitement about new technology and foster a culture of experimentation, play, and wonder.\"), \" We\\u2019re excited about reaching our goals and love to tinker. People are constantly creating incredible things, and it\\u2019s critical both to our success as a company \", mdx(\"em\", {\n    parentName: \"p\"\n  }, \"and\"), \" to our happiness as geeks that we take time to play with these incredible new technologies.\"), mdx(\"h3\", {\n    \"id\": \"you-belong-here\"\n  }, mdx(\"a\", _extends({\n    parentName: \"h3\"\n  }, {\n    \"href\": \"#you-belong-here\",\n    \"aria-label\": \"you belong here permalink\",\n    \"className\": \"anchor\"\n  }), mdx(\"svg\", _extends({\n    parentName: \"a\"\n  }, {\n    \"aria-hidden\": \"true\",\n    \"focusable\": \"false\",\n    \"height\": \"16\",\n    \"version\": \"1.1\",\n    \"viewBox\": \"0 0 16 16\",\n    \"width\": \"16\"\n  }), mdx(\"path\", _extends({\n    parentName: \"svg\"\n  }, {\n    \"fillRule\": \"evenodd\",\n    \"d\": \"M4 9h1v1H4c-1.5 0-3-1.69-3-3.5S2.55 3 4 3h4c1.45 0 3 1.69 3 3.5 0 1.41-.91 2.72-2 3.25V8.59c.58-.45 1-1.27 1-2.09C10 5.22 8.98 4 8 4H4c-.98 0-2 1.22-2 2.5S3 9 4 9zm9-3h-1v1h1c1 0 2 1.22 2 2.5S13.98 12 13 12H9c-.98 0-2-1.22-2-2.5 0-.83.42-1.64 1-2.09V6.25c-1.09.53-2 1.84-2 3.25C6 11.31 7.55 13 9 13h4c1.45 0 3-1.69 3-3.5S14.5 6 13 6z\"\n  })))), \"You belong here\"), mdx(\"p\", null, \"Open source doesn\\u2019t have the best reputation for being friendly and welcoming, and that makes us sad. \", mdx(\"strong\", {\n    parentName: \"p\"\n  }, \"Everyone belongs in open source, and Gatsby is dedicated to making you feel welcome.\")), mdx(\"p\", null, \"We will never judge, condescend, or exclude anyone. Instead, we will go above and beyond to support the community, through \", mdx(\"a\", _extends({\n    parentName: \"p\"\n  }, {\n    \"href\": \"https://gatsby.dev/pairing\"\n  }), \"pair programming\"), \", offering \", mdx(\"a\", _extends({\n    parentName: \"p\"\n  }, {\n    \"href\": \"https://gatsby.dev/swag\"\n  }), \"free swag for contributors\"), \", giving control to the community by \", mdx(\"a\", _extends({\n    parentName: \"p\"\n  }, {\n    \"href\": \"https://github.com/gatsbyjs/gatsby/pull/7699#issuecomment-416665803\"\n  }), \"auto-inviting all contributors to the Gatsby GitHub org\"), \", an open and inclusive \", mdx(\"a\", _extends({\n    parentName: \"p\"\n  }, {\n    \"href\": \"/contributing/code-of-conduct/\"\n  }), \"code of conduct\"), \", and other means that empower and embrace the incredible community that makes Gatsby possible.\"), mdx(\"blockquote\", {\n    className: \"twitter-tweet\",\n    \"data-lang\": \"en\"\n  }, mdx(\"p\", {\n    lang: \"en\",\n    dir: \"ltr\"\n  }, \"Huge shoutout to\", \" \", mdx(\"a\", {\n    href: \"https://twitter.com/gatsbyjs?ref_src=twsrc%5Etfw\"\n  }, \"@gatsbyjs\"), \". Not only have hey been the perfect open source project for Lambda School students to contribute to, but the whole community goes above and beyond in helping students understand the OSS ecosystem generally\"), \"\\u2014 Austen Allred (@AustenAllred)\", \" \", mdx(\"a\", {\n    href: \"https://twitter.com/AustenAllred/status/1038084753008652289?ref_src=twsrc%5Etfw\"\n  }, \"September 7, 2018\")), mdx(\"p\", null, \"We\\u2019re so happy you\\u2019re here. \\uD83D\\uDCAA\\uD83D\\uDC9C\"), mdx(\"h2\", {\n    \"id\": \"how-our-company-values-will-affect-us-going-forward\"\n  }, mdx(\"a\", _extends({\n    parentName: \"h2\"\n  }, {\n    \"href\": \"#how-our-company-values-will-affect-us-going-forward\",\n    \"aria-label\": \"how our company values will affect us going forward permalink\",\n    \"className\": \"anchor\"\n  }), mdx(\"svg\", _extends({\n    parentName: \"a\"\n  }, {\n    \"aria-hidden\": \"true\",\n    \"focusable\": \"false\",\n    \"height\": \"16\",\n    \"version\": \"1.1\",\n    \"viewBox\": \"0 0 16 16\",\n    \"width\": \"16\"\n  }), mdx(\"path\", _extends({\n    parentName: \"svg\"\n  }, {\n    \"fillRule\": \"evenodd\",\n    \"d\": \"M4 9h1v1H4c-1.5 0-3-1.69-3-3.5S2.55 3 4 3h4c1.45 0 3 1.69 3 3.5 0 1.41-.91 2.72-2 3.25V8.59c.58-.45 1-1.27 1-2.09C10 5.22 8.98 4 8 4H4c-.98 0-2 1.22-2 2.5S3 9 4 9zm9-3h-1v1h1c1 0 2 1.22 2 2.5S13.98 12 13 12H9c-.98 0-2-1.22-2-2.5 0-.83.42-1.64 1-2.09V6.25c-1.09.53-2 1.84-2 3.25C6 11.31 7.55 13 9 13h4c1.45 0 3-1.69 3-3.5S14.5 6 13 6z\"\n  })))), \"How our company values will affect us going forward\"), mdx(\"p\", null, \"As a stand-alone list, these values are a great list of aspirational ideas, but they won\\u2019t mean much if we don\\u2019t put them into practice.\"), mdx(\"p\", null, \"To ensure we live and work according to these values, we\\u2019re using our values as a key factor in our decision making process. As we put together our roadmap, define our internal workflow processes, or even plan a tweet or GitHub response, we\\u2019ll be asking if the thing we\\u2019re about to do is lined up with our values.\"), mdx(\"p\", null, \"Are we acting like the company we want to be? Like the \", mdx(\"em\", {\n    parentName: \"p\"\n  }, \"people\"), \" we want to be?\"), mdx(\"figure\", null, \"\\n  \", mdx(\"span\", _extends({\n    parentName: \"figure\"\n  }, {\n    \"className\": \"gatsby-resp-image-wrapper\",\n    \"style\": {\n      \"position\": \"relative\",\n      \"display\": \"block\",\n      \"marginLeft\": \"auto\",\n      \"marginRight\": \"auto\",\n      \"maxWidth\": \"786px\"\n    }\n  }), \"\\n      \", mdx(\"a\", _extends({\n    parentName: \"span\"\n  }, {\n    \"className\": \"gatsby-resp-image-link\",\n    \"href\": \"/static/cd925e21931da051257fbb9b993885a2/d7d8f/team-in-the-park.jpg\",\n    \"style\": {\n      \"display\": \"block\"\n    },\n    \"target\": \"_blank\",\n    \"rel\": [\"noopener\"]\n  }), \"\\n    \", mdx(\"span\", _extends({\n    parentName: \"a\"\n  }, {\n    \"className\": \"gatsby-resp-image-background-image\",\n    \"style\": {\n      \"paddingBottom\": \"55.00000000000001%\",\n      \"position\": \"relative\",\n      \"bottom\": \"0\",\n      \"left\": \"0\",\n      \"backgroundImage\": \"url('data:image/jpeg;base64,/9j/2wBDABALDA4MChAODQ4SERATGCgaGBYWGDEjJR0oOjM9PDkzODdASFxOQERXRTc4UG1RV19iZ2hnPk1xeXBkeFxlZ2P/2wBDARESEhgVGC8aGi9jQjhCY2NjY2NjY2NjY2NjY2NjY2NjY2NjY2NjY2NjY2NjY2NjY2NjY2NjY2NjY2NjY2NjY2P/wgARCAALABQDASIAAhEBAxEB/8QAGAAAAgMAAAAAAAAAAAAAAAAAAAECAwX/xAAVAQEBAAAAAAAAAAAAAAAAAAABAv/aAAwDAQACEAMQAAABcs0ltGFf/8QAGxAAAwACAwAAAAAAAAAAAAAAAQIDABEhMTL/2gAIAQEAAQUCk4OGy6o4LjjD1Hx//8QAFREBAQAAAAAAAAAAAAAAAAAAABH/2gAIAQMBAT8BR//EABURAQEAAAAAAAAAAAAAAAAAAAAR/9oACAECAQE/AVf/xAAZEAEAAgMAAAAAAAAAAAAAAAABABACEVH/2gAIAQEABj8CMSmbOX//xAAbEAACAgMBAAAAAAAAAAAAAAABEQAhMUFRsf/aAAgBAQABPyEwAyrMKwxyFBN8hFyEERu2x5LObuf/2gAMAwEAAgADAAAAEAf/AP/EABYRAQEBAAAAAAAAAAAAAAAAACEAAf/aAAgBAwEBPxAm5f/EABcRAAMBAAAAAAAAAAAAAAAAAAABIRH/2gAIAQIBAT8QxEQ//8QAGhABAAMBAQEAAAAAAAAAAAAAAQARITFBYf/aAAgBAQABPxAya6FL+Rm95eamsZWqomwLRFsV2EEeiv2qTPqVrP/Z')\",\n      \"backgroundSize\": \"cover\",\n      \"display\": \"block\"\n    }\n  })), \"\\n  \", mdx(\"img\", _extends({\n    parentName: \"a\"\n  }, {\n    \"className\": \"gatsby-resp-image-image\",\n    \"alt\": \"The Gatsby Inkteam together in a park.\",\n    \"title\": \"The Gatsby Inkteam together in a park.\",\n    \"src\": \"/static/cd925e21931da051257fbb9b993885a2/a022f/team-in-the-park.jpg\",\n    \"srcSet\": [\"/static/cd925e21931da051257fbb9b993885a2/28bf1/team-in-the-park.jpg 197w\", \"/static/cd925e21931da051257fbb9b993885a2/afe26/team-in-the-park.jpg 393w\", \"/static/cd925e21931da051257fbb9b993885a2/a022f/team-in-the-park.jpg 786w\", \"/static/cd925e21931da051257fbb9b993885a2/6ff56/team-in-the-park.jpg 1179w\", \"/static/cd925e21931da051257fbb9b993885a2/b5562/team-in-the-park.jpg 1572w\", \"/static/cd925e21931da051257fbb9b993885a2/d7d8f/team-in-the-park.jpg 2400w\"],\n    \"sizes\": \"(max-width: 786px) 100vw, 786px\",\n    \"loading\": \"lazy\"\n  })), \"\\n  \"), \"\\n    \"), \"\\n  \", mdx(\"figcaption\", {\n    parentName: \"figure\"\n  }, \"\\n    The Gatsby Inkteam (not pictured: Florian Kissling). Photo:{\\\" \\\"}\\n    \", mdx(\"a\", _extends({\n    parentName: \"figcaption\"\n  }, {\n    \"href\": \"https://www.houseofschaab.photography/\"\n  }), \"Danielle Schaab\"), \"\\n  \")), mdx(\"p\", null, \"It\\u2019s too early for any definitive results, but so far we\\u2019ve heard these values come up in meetings and discussions to keep things headed in the right direction. And \\u2014 speaking personally \\u2014 it feels \", mdx(\"em\", {\n    parentName: \"p\"\n  }, \"really dang good\"), \" to be on a team that saw the importance of doing the upfront work to write these values down. I\\u2019m very proud to be part of the Gatsby Inkteam, and extremely grateful to be part of such an incredible open source community.\"), mdx(\"p\", null, \"Come \", mdx(\"a\", _extends({\n    parentName: \"p\"\n  }, {\n    \"href\": \"https://twitter.com/jlengstorf\"\n  }), \"say hi on Twitter\"), \" and \", mdx(\"a\", _extends({\n    parentName: \"p\"\n  }, {\n    \"href\": \"https://github.com/gatsbyjs/gatsby/issues#boards?filterLogic=any\"\n  }), \"dive into our open issues\"), \".\"), mdx(\"p\", null, \"Y\\u2019all are the best. \\uD83D\\uDC9C\"));\n}\n;\nMDXContent.isMDXComponent = true;",
        "excerpt": "Most of the Gatsby  Inkteam  was together in Portland last week for our latest team onsite, which we lovingly refer to as “Gatsby Gatherings…",
        "timeToRead": 6,
        "fields": {
          "slug": "/blog/2018-09-07-gatsby-values/",
          "publishedAt": null
        },
        "frontmatter": {
          "title": "What kind of company will we be? A look at Gatsby’s mission and values.",
          "excerpt": null,
          "date": "September 7th 2018",
          "rawDate": "2018-09-07T00:00:00.000Z",
          "canonicalLink": null,
          "tags": [
            "gatsby-inc"
          ],
          "image": {
            "childImageSharp": {
              "resize": {
                "src": "/static/0fb8ce7959ce96d707cc3a274c905dd8/b3ea4/values-whiteboard.jpg"
              },
              "fluid": {
                "base64": "data:image/jpeg;base64,/9j/2wBDABALDA4MChAODQ4SERATGCgaGBYWGDEjJR0oOjM9PDkzODdASFxOQERXRTc4UG1RV19iZ2hnPk1xeXBkeFxlZ2P/2wBDARESEhgVGC8aGi9jQjhCY2NjY2NjY2NjY2NjY2NjY2NjY2NjY2NjY2NjY2NjY2NjY2NjY2NjY2NjY2NjY2NjY2P/wgARCAALABQDASIAAhEBAxEB/8QAGQAAAgMBAAAAAAAAAAAAAAAAAAIBAwQF/8QAFAEBAAAAAAAAAAAAAAAAAAAAAf/aAAwDAQACEAMQAAAB0vUwQc8T/8QAGxAAAgIDAQAAAAAAAAAAAAAAAQIDESExMkP/2gAIAQEAAQUCm58UktH1eAaH/8QAFhEBAQEAAAAAAAAAAAAAAAAAAAES/9oACAEDAQE/AWa//8QAFREBAQAAAAAAAAAAAAAAAAAAABH/2gAIAQIBAT8BV//EABcQAQEBAQAAAAAAAAAAAAAAAAEAgZH/2gAIAQEABj8ChYbkbF//xAAaEAEAAgMBAAAAAAAAAAAAAAABABEhMVFB/9oACAEBAAE/IcPJj2C0lNZhMu47y7Cm/kKI1XJ//9oADAMBAAIAAwAAABDfz//EABcRAAMBAAAAAAAAAAAAAAAAAAABEXH/2gAIAQMBAT8QlWjsf//EABYRAQEBAAAAAAAAAAAAAAAAAAEAEf/aAAgBAgEBPxDQg3//xAAaEAEBAQEBAQEAAAAAAAAAAAABEQAhMVFh/9oACAEBAAE/EEiqE1XHzmGQ6QNmhgmh8MhcMAp4YbVLSfrmrAccb//Z",
                "aspectRatio": 1.8181818181818181,
                "src": "/static/0fb8ce7959ce96d707cc3a274c905dd8/51ce9/values-whiteboard.jpg",
                "srcSet": "/static/0fb8ce7959ce96d707cc3a274c905dd8/35dbd/values-whiteboard.jpg 197w,\n/static/0fb8ce7959ce96d707cc3a274c905dd8/c77ca/values-whiteboard.jpg 393w,\n/static/0fb8ce7959ce96d707cc3a274c905dd8/51ce9/values-whiteboard.jpg 786w,\n/static/0fb8ce7959ce96d707cc3a274c905dd8/9a55b/values-whiteboard.jpg 1179w,\n/static/0fb8ce7959ce96d707cc3a274c905dd8/005c4/values-whiteboard.jpg 1572w,\n/static/0fb8ce7959ce96d707cc3a274c905dd8/c82f6/values-whiteboard.jpg 2400w",
                "sizes": "(max-width: 786px) 100vw, 786px"
              }
            }
          },
          "imageAuthor": null,
          "imageAuthorLink": null,
          "imageTitle": null,
          "showImageInArticle": false,
          "author": {
            "id": "Jason Lengstorf",
            "bio": "Developer. Occasional designer. Process and culture architect. Mediocre bartender. Blogs at lengstorf.com",
            "twitter": "@jlengstorf",
            "avatar": {
              "childImageSharp": {
                "fixed": {
                  "tracedSVG": "data:image/svg+xml,%3csvg%20xmlns='http://www.w3.org/2000/svg'%20width='32'%20height='32'%3e%3crect%20width='100%25'%20height='100%25'%20fill='%23f6f2f8'/%3e%3cpath%20d='M0%205c0%204%200%205%201%204%202-3%204-2%204%202l-1%205-1-1-1%201c-2%202-2%209-1%2010v1l-1%203v2h33v-5c0-4-1-5-2-5l-2-3%203%201c1%201%201%201%201-1l-2-4v1c1%202%201%202-1%202l-3-1-3-6c0%204-3%209-4%206h-9c-2-2%200-4%203-4l6-1-1-2-1%201-4%201-4%201c-1%201-1%200-1-3%201-5%201-5-5-5-2%200-3-1-3-3-1-2-1-1-1%203m20%2018l-3%202c-2%201-1%201%201%201l4-2c0-2-2-3-2-1'%20fill='%23e0d6eb'%20fill-rule='evenodd'/%3e%3c/svg%3e",
                  "width": 64,
                  "height": 64,
                  "src": "/static/592a909abf7885f0c711184295d5abeb/88ae8/jason-lengstorf.jpg",
                  "srcSet": "/static/592a909abf7885f0c711184295d5abeb/88ae8/jason-lengstorf.jpg 1x,\n/static/592a909abf7885f0c711184295d5abeb/0740f/jason-lengstorf.jpg 1.5x,\n/static/592a909abf7885f0c711184295d5abeb/c9264/jason-lengstorf.jpg 2x"
                }
              }
            },
            "fields": {
              "slug": "/contributors/jason-lengstorf/"
            }
          }
        }
      }
    },
    "pageContext": {
      "isCreatedByStatefulCreatePages": false,
      "slug": "/blog/2018-09-07-gatsby-values/",
      "prev": {
        "fields": {
          "slug": "/blog/2018-08-24-gatsby-aws-hosting/",
          "package": null,
          "released": true
        },
        "frontmatter": {
          "title": "Publishing Your Next Gatsby Site to AWS With AWS Amplify",
          "draft": null,
          "canonicalLink": "https://aws-amplify.github.io/amplify-js/media/hosting_guide",
          "publishedAt": null,
          "issue": null,
          "tags": [
            "serverless",
            "hosting",
            "blogs",
            "aws"
          ]
        }
      },
      "next": {
        "fields": {
          "slug": "/blog/2018-09-17-gatsby-v2/",
          "package": null,
          "released": true
        },
        "frontmatter": {
          "title": "Announcing Gatsby 2.0.0 🎉🎉🎉",
          "draft": null,
          "canonicalLink": null,
          "publishedAt": null,
          "issue": null,
          "tags": null
        }
      }
    }
  },
  "query": "query usersMisiekDevGatsbyWwwSrcTemplatesTemplateBlogPostJs2991924798(\n  $slug: String!\n) {\n  mdx(fields: {slug: {eq: $slug}}) {\n    body\n    excerpt\n    timeToRead\n    fields {\n      slug\n      publishedAt\n    }\n    frontmatter {\n      title\n      excerpt\n      date(formatString: \"MMMM Do YYYY\")\n      rawDate: date\n      canonicalLink\n      tags\n      image {\n        childImageSharp {\n          resize(width: 1500, height: 1500) {\n            src\n          }\n          fluid(maxWidth: 786) {\n            ...GatsbyImageSharpFluid\n          }\n        }\n      }\n      imageAuthor\n      imageAuthorLink\n      imageTitle\n      showImageInArticle\n      author {\n        id\n        bio\n        twitter\n        avatar {\n          childImageSharp {\n            fixed(width: 64, height: 64, quality: 75, traceSVG: {turdSize: 10, background: \"#f6f2f8\", color: \"#e0d6eb\"}) {\n              ...GatsbyImageSharpFixed_tracedSVG\n            }\n          }\n        }\n        fields {\n          slug\n        }\n      }\n    }\n  }\n}\n\nfragment GatsbyImageSharpFluid on ImageSharpFluid {\n  base64\n  aspectRatio\n  src\n  srcSet\n  sizes\n}\n\nfragment GatsbyImageSharpFixed_tracedSVG on ImageSharpFixed {\n  tracedSVG\n  width\n  height\n  src\n  srcSet\n}\n"
}