{
  "path": "/packages/@moltin/gatsby-source-moltin/",
  "result": {
    "data": {
      "markdownRemark": null,
      "npmPackage": {
        "name": "@moltin/gatsby-source-moltin",
        "description": "Gatsby source plugin for building Moltin powered eCommerce websites",
        "keywords": [
          "gatsby",
          "gatsby-plugin",
          "gatsby-source-plugin",
          "moltin"
        ],
        "lastPublisher": {
          "name": "moltinbot",
          "avatar": "https://gravatar.com/avatar/3173b791fabeafbd9bde0ac3a622996b"
        },
        "repository": {
          "url": "https://github.com/moltin/gatsby-source-moltin"
        },
        "readme": {
          "childMarkdownRemark": {
            "html": "<h1 id=\"gatsby-source-moltin\"><a href=\"#gatsby-source-moltin\" aria-label=\"gatsby source moltin permalink\" class=\"anchor\"><svg aria-hidden=\"true\" focusable=\"false\" height=\"16\" version=\"1.1\" viewBox=\"0 0 16 16\" width=\"16\"><path fill-rule=\"evenodd\" d=\"M4 9h1v1H4c-1.5 0-3-1.69-3-3.5S2.55 3 4 3h4c1.45 0 3 1.69 3 3.5 0 1.41-.91 2.72-2 3.25V8.59c.58-.45 1-1.27 1-2.09C10 5.22 8.98 4 8 4H4c-.98 0-2 1.22-2 2.5S3 9 4 9zm9-3h-1v1h1c1 0 2 1.22 2 2.5S13.98 12 13 12H9c-.98 0-2-1.22-2-2.5 0-.83.42-1.64 1-2.09V6.25c-1.09.53-2 1.84-2 3.25C6 11.31 7.55 13 9 13h4c1.45 0 3-1.69 3-3.5S14.5 6 13 6z\"></path></svg></a>gatsby-source-moltin</h1>\n<p>🚀 Gatsby source plugin for building <a href=\"https://moltin.com\">Moltin</a> powered eCommerce websites.</p>\n<h2 id=\"install\"><a href=\"#install\" aria-label=\"install permalink\" class=\"anchor\"><svg aria-hidden=\"true\" focusable=\"false\" height=\"16\" version=\"1.1\" viewBox=\"0 0 16 16\" width=\"16\"><path fill-rule=\"evenodd\" d=\"M4 9h1v1H4c-1.5 0-3-1.69-3-3.5S2.55 3 4 3h4c1.45 0 3 1.69 3 3.5 0 1.41-.91 2.72-2 3.25V8.59c.58-.45 1-1.27 1-2.09C10 5.22 8.98 4 8 4H4c-.98 0-2 1.22-2 2.5S3 9 4 9zm9-3h-1v1h1c1 0 2 1.22 2 2.5S13.98 12 13 12H9c-.98 0-2-1.22-2-2.5 0-.83.42-1.64 1-2.09V6.25c-1.09.53-2 1.84-2 3.25C6 11.31 7.55 13 9 13h4c1.45 0 3-1.69 3-3.5S14.5 6 13 6z\"></path></svg></a>Install</h2>\n<div class=\"gatsby-highlight\" data-language=\"sh\"><pre class=\"language-sh\"><code class=\"language-sh\">yarn add @moltin/gatsby-source-moltin</code></pre></div>\n<h2 id=\"how-to-use\"><a href=\"#how-to-use\" aria-label=\"how to use permalink\" class=\"anchor\"><svg aria-hidden=\"true\" focusable=\"false\" height=\"16\" version=\"1.1\" viewBox=\"0 0 16 16\" width=\"16\"><path fill-rule=\"evenodd\" d=\"M4 9h1v1H4c-1.5 0-3-1.69-3-3.5S2.55 3 4 3h4c1.45 0 3 1.69 3 3.5 0 1.41-.91 2.72-2 3.25V8.59c.58-.45 1-1.27 1-2.09C10 5.22 8.98 4 8 4H4c-.98 0-2 1.22-2 2.5S3 9 4 9zm9-3h-1v1h1c1 0 2 1.22 2 2.5S13.98 12 13 12H9c-.98 0-2-1.22-2-2.5 0-.83.42-1.64 1-2.09V6.25c-1.09.53-2 1.84-2 3.25C6 11.31 7.55 13 9 13h4c1.45 0 3-1.69 3-3.5S14.5 6 13 6z\"></path></svg></a>How to use</h2>\n<div class=\"gatsby-highlight\" data-language=\"js\"><pre class=\"language-js\"><code class=\"language-js\"><span class=\"token comment\">// In your gatsby-config.js</span>\nplugins<span class=\"token punctuation\">:</span> <span class=\"token punctuation\">[</span>\n  <span class=\"token punctuation\">{</span>\n    resolve<span class=\"token punctuation\">:</span> <span class=\"token template-string\"><span class=\"token template-punctuation string\">`</span><span class=\"token string\">@moltin/gatsby-source-moltin</span><span class=\"token template-punctuation string\">`</span></span><span class=\"token punctuation\">,</span>\n    options<span class=\"token punctuation\">:</span> <span class=\"token punctuation\">{</span>\n      client_id<span class=\"token punctuation\">:</span> <span class=\"token string\">'...'</span>\n    <span class=\"token punctuation\">}</span><span class=\"token punctuation\">,</span>\n  <span class=\"token punctuation\">}</span><span class=\"token punctuation\">,</span>\n<span class=\"token punctuation\">]</span><span class=\"token punctuation\">,</span></code></pre></div>\n<h2 id=\"how-to-query\"><a href=\"#how-to-query\" aria-label=\"how to query permalink\" class=\"anchor\"><svg aria-hidden=\"true\" focusable=\"false\" height=\"16\" version=\"1.1\" viewBox=\"0 0 16 16\" width=\"16\"><path fill-rule=\"evenodd\" d=\"M4 9h1v1H4c-1.5 0-3-1.69-3-3.5S2.55 3 4 3h4c1.45 0 3 1.69 3 3.5 0 1.41-.91 2.72-2 3.25V8.59c.58-.45 1-1.27 1-2.09C10 5.22 8.98 4 8 4H4c-.98 0-2 1.22-2 2.5S3 9 4 9zm9-3h-1v1h1c1 0 2 1.22 2 2.5S13.98 12 13 12H9c-.98 0-2-1.22-2-2.5 0-.83.42-1.64 1-2.09V6.25c-1.09.53-2 1.84-2 3.25C6 11.31 7.55 13 9 13h4c1.45 0 3-1.69 3-3.5S14.5 6 13 6z\"></path></svg></a>How to query</h2>\n<div class=\"gatsby-highlight\" data-language=\"graphql\"><pre class=\"language-graphql\"><code class=\"language-graphql\"><span class=\"token punctuation\">{</span>\n  allMoltinProduct <span class=\"token punctuation\">{</span>\n    edges <span class=\"token punctuation\">{</span>\n      node <span class=\"token punctuation\">{</span>\n        id\n        name\n        description\n        slug\n        sku\n        categories <span class=\"token punctuation\">{</span>\n          id\n          name\n        <span class=\"token punctuation\">}</span>\n      <span class=\"token punctuation\">}</span>\n    <span class=\"token punctuation\">}</span>\n  <span class=\"token punctuation\">}</span>\n<span class=\"token punctuation\">}</span></code></pre></div>",
            "timeToRead": 1
          }
        }
      }
    },
    "pageContext": {
      "isCreatedByStatefulCreatePages": false,
      "slug": "/packages/@moltin/gatsby-source-moltin/",
      "id": "5f6a9d93-8220-530f-a65f-6aac184b0918",
      "layout": "plugins"
    }
  },
  "query": "query usersMisiekDevGatsbyWwwSrcTemplatesTemplateDocsRemotePackagesJs803499274(\n  $slug: String!\n) {\n  markdownRemark(fields: {slug: {eq: $slug}}) {\n    ...MarkdownPageFooter\n  }\n  npmPackage(slug: {eq: $slug}) {\n    name\n    description\n    keywords\n    lastPublisher {\n      name\n      avatar\n    }\n    repository {\n      url\n    }\n    readme {\n      childMarkdownRemark {\n        html\n        timeToRead\n      }\n    }\n  }\n}\n\nfragment MarkdownPageFooter on MarkdownRemark {\n  parent {\n    __typename\n    ... on File {\n      relativePath\n    }\n  }\n}\n"
}